Workbook

Sheet Sales Ramp
A1: SaaS Economics - Ramping a SaaS salesforce
H2: Cells formated like this: | J2: are input variables
A4: Part 1: Model the ecomomics of a single sales person
A5: Sales compensation and overhead
A6: Base Compensation | B6: 50000
A7: Variable Compensation | B7: 55000 | C7: with 50% draw for first four months
A8: Draw on Variable Comp | B8: 1 | C8: 0.7 | D8: 0.3 | E8: 0 | F8: 0 | G8: 0 | H8: 0 | I8: 0 | J8: 0
A9: Productivity Ramp | B9: 0.1 | C9: 0.33 | D9: 0.66 | E9: 1 | F9: 1 | G9: 1 | H9: 1 | I9: 1 | J9: 1
A10: Additional overhead | B10: 30000
A11: Sales attrition factor | B11: 0.15 | C11: a factor to discount bookings to account for failed sales hires and attrition
A13: On target annual bookings
A14: Annual Bookings | B14: 500000 | C14: ACV (Annual Contract Value)
A15: Monthly Bookings | B15: =B14/12 -> 41666.667 | C15: ACV (Annual Contract Value)
A16: Monthly Bookings | B16: =B15/12 -> 3472.2222 | C16: Billed monthly (=ACV / 12) | H16: Quick Marketing Calculation
H17: 0.5 | I17: amount of traffic that is organic versus paid
A18: Churn Rate and Margin | H18: 1.5 | I18: cost per paid visitor (Google AdWords, etc.)
A19: Churn Rate (monthly) | B19: 0.025 | H19: =H18*(1-H17) -> 0.75 | I19: Cost per visitor (both paid and unpaid)
A20: Gross Margin | B20: 0.8 | H20: 0.03 | I20: visitors convert to raw leads
H21: 0.2 | I21: number of raw leads that turn into qualified leads
A22: Cost of Leads required to feed sales
A23: Average Deal Size | B23: 6000 | C23: (ACV) Annual Contract Value
A24: Deals to meet target | B24: =B15/B23 -> 6.9444444 | C24: per month | H24: 1 | I24: qualified lead
A25: Leads to closed deal | B25: 10 | H25: =H24/H21 -> 5 | I25: raw leads required
A26: Cost per Qualified Lead | B26: =H27 -> 125.25 | H26: =ROUND(H25/H20,0) -> 167 | I26: visitors required
A27: Cost of Leads required | B27: =B26*B24*B25 -> 8697.9167 | C27: per month, for 1 fully productive sales person | H27: =H26*H19 -> 125.25 | I27: Cost of visitors (also = Cost per qualified lead)
A30: Other interesting Calculations
A31: Lead Gen costs per deal | B31: =B26*B25 -> 1252.5 | C31: Excludes people costs
A32: Selling costs per deal | B32: =(B6+B7+B10)/12/B24 -> 1620 | C32: Excludes cost of sales management
A33: Total CAC | B33: =B32+B31 -> 2872.5 | C33: Excludes people costs in marketing, and sales management. (CAC= Cost to Acquire a Customer)
A34: Total LTV | B34: =B23*B20/12/B19 -> 16000 | C34: Calculated by dividing average monthly gross profit per customer (ARPU x Gross Margin ) by the churn rate
A37: Income | B37: Month 1 | C37: Month 2 | D37: Month 3 | E37: Month 4 | F37: Month 5 | G37: Month 6 | H37: Month 7 | I37: Month 8 | J37: Month 9 | K37: Month 10 | L37: Month 11 | M37: Month 12 | N37: Month 13 | O37: Month 14 | P37: Month 15 | Q37: Month 16 | R37: Month 17 | S37: Month 18 | T37: Month 19 | U37: Month 20 | V37: Month 21 | W37: Month 22 | X37: Month 23 | Y37: Month 24 | Z37: Month 25 | AA37: Month 26 | AB37: Month 27 | AC37: Month 28 | AD37: Month 29 | AE37: Month 30 | AF37: Month 31 | AG37: Month 32 | AH37: Month 33 | AI37: Month 34 | AJ37: Month 35 | AK37: Month 36
A38: Productivity Ramp | B38: =B9 -> 0.1 | C38: =C9 -> 0.33 | D38: =D9 -> 0.66 | E38: =E9 -> 1 | F38: =F9 -> 1 | G38: =G9 -> 1 | H38: =H9 -> 1 | I38: =I9 -> 1 | J38: =J9 -> 1 | K38: 1 | L38: 1 | M38: 1 | N38: 1 | O38: 1 | P38: 1 | Q38: 1 | R38: 1 | S38: 1 | T38: 1 | U38: 1 | V38: 1 | W38: 1 | X38: 1 | Y38: 1 | Z38: 1 | AA38: 1 | AB38: 1 | AC38: 1 | AD38: 1 | AE38: 1 | AF38: 1 | AG38: 1 | AH38: 1 | AI38: 1 | AJ38: 1 | AK38: 1
A39: Bookings (ACV) | B39: =B38*$B$15*(1-$B$11) -> 3541.6667 | C39: =C38*$B$15*(1-$B$11) -> 11687.5 | D39: =D38*$B$15*(1-$B$11) -> 23375 | E39: =E38*$B$15*(1-$B$11) -> 35416.667 | F39: =F38*$B$15*(1-$B$11) -> 35416.667 | G39: =G38*$B$15*(1-$B$11) -> 35416.667 | H39: =H38*$B$15*(1-$B$11) -> 35416.667 | I39: =I38*$B$15*(1-$B$11) -> 35416.667 | ... AK39: =AK38*$B$15*(1-$B$11) -> 35416.667
A40: New MRR added this month | B40: =B39/12 -> 295.13889 | C40: =C39/12 -> 973.95833 | D40: =D39/12 -> 1947.9167 | E40: =E39/12 -> 2951.3889 | F40: =F39/12 -> 2951.3889 | G40: =G39/12 -> 2951.3889 | H40: =H39/12 -> 2951.3889 | I40: =I39/12 -> 2951.3889 | ... AK40: =AK39/12 -> 2951.3889
A41: MRR from prior months bookings | C41: =B40 -> 295.13889 | D41: =C40+C41+C42 -> 1261.7188 | E41: =D40+D41+D42 -> 3178.0924 | F41: =E40+E41+E42 -> 6050.029 | G41: =F40+F41+F42 -> 8850.1672 | H41: =G40+G41+G42 -> 11580.302 | I41: =H40+H41+H42 -> 14242.183 | J41: =I40+I41+I42 -> 16837.518 | K41: =J40+J41+J42 -> 19367.968 | ... AK41: =AJ40+AJ41+AJ42 -> 66960.069
A42: Churn | C42: =-$B$19*C41 -> -7.3784722 | D42: =-$B$19*D41 -> -31.542969 | E42: =-$B$19*E41 -> -79.452311 | F42: =-$B$19*F41 -> -151.25073 | G42: =-$B$19*G41 -> -221.25418 | H42: =-$B$19*H41 -> -289.50755 | I42: =-$B$19*I41 -> -356.05458 | J42: =-$B$19*J41 -> -420.93794 | ... AK42: =-$B$19*AK41 -> -1674.0017
A43: Total MRR (Billings) | B43: =SUM(B40:B42) -> 295.13889 | C43: =SUM(C40:C42) -> 1261.7188 | D43: =SUM(D40:D42) -> 3178.0924 | E43: =SUM(E40:E42) -> 6050.029 | F43: =SUM(F40:F42) -> 8850.1672 | G43: =SUM(G40:G42) -> 11580.302 | H43: =SUM(H40:H42) -> 14242.183 | I43: =SUM(I40:I42) -> 16837.518 | ... AK43: =SUM(AK40:AK42) -> 68237.456
A44: Cumulative Billings | B44: =B43 -> 295.13889 | C44: =B44+C43 -> 1556.8576 | D44: =C44+D43 -> 4734.9501 | E44: =D44+E43 -> 10784.979 | F44: =E44+F43 -> 19635.146 | G44: =F44+G43 -> 31215.448 | H44: =G44+H43 -> 45457.631 | I44: =H44+I43 -> 62295.149 | J44: =I44+J43 -> 81663.117 | ... AK44: =AJ44+AK43 -> 1363253.1
A45: Cumulative Gross Profit | B45: =$B$20*B44 -> 236.11111 | C45: =$B$20*C44 -> 1245.4861 | D45: =$B$20*D44 -> 3787.9601 | E45: =$B$20*E44 -> 8627.9833 | F45: =$B$20*F44 -> 15708.117 | G45: =$B$20*G44 -> 24972.359 | H45: =$B$20*H44 -> 36366.105 | I45: =$B$20*I44 -> 49836.119 | ... AK45: =$B$20*AK44 -> 1090602.5
A48: Expenses
A49: Base Salary | B49: =$B$6/12 -> 4166.6667 | C49: =$B$6/12 -> 4166.6667 | D49: =$B$6/12 -> 4166.6667 | E49: =$B$6/12 -> 4166.6667 | F49: =$B$6/12 -> 4166.6667 | G49: =$B$6/12 -> 4166.6667 | H49: =$B$6/12 -> 4166.6667 | I49: =$B$6/12 -> 4166.6667 | ... AK49: =$B$6/12 -> 4166.6667
A50: Variable Compensation | B50: =MAX(B38,B8)*$B$7/12 -> 4583.3333 | C50: =MAX(C38,C8)*$B$7/12 -> 3208.3333 | D50: =MAX(D38,D8)*$B$7/12 -> 3025 | E50: =MAX(E38,E8)*$B$7/12 -> 4583.3333 | F50: =MAX(F38,F8)*$B$7/12 -> 4583.3333 | G50: =MAX(G38,G8)*$B$7/12 -> 4583.3333 | H50: =MAX(H38,H8)*$B$7/12 -> 4583.3333 | I50: =MAX(I38,I8)*$B$7/12 -> 4583.3333 | J50: =MAX(J38,J8)*$B$7/12 -> 4583.3333 | K50: =$B$7/12 -> 4583.3333 | L50: =$B$7/12 -> 4583.3333 | M50: =$B$7/12 -> 4583.3333 | N50: =$B$7/12 -> 4583.3333 | O50: =$B$7/12 -> 4583.3333 | P50: =$B$7/12 -> 4583.3333 | Q50: =$B$7/12 -> 4583.3333 | R50: =$B$7/12 -> 4583.3333 | ... AK50: =$B$7/12 -> 4583.3333
A51: Overhead | B51: =$B$10/12 -> 2500 | C51: =$B$10/12 -> 2500 | D51: =$B$10/12 -> 2500 | E51: =$B$10/12 -> 2500 | F51: =$B$10/12 -> 2500 | G51: =$B$10/12 -> 2500 | H51: =$B$10/12 -> 2500 | I51: =$B$10/12 -> 2500 | ... AK51: =$B$10/12 -> 2500
A52: Cost of leads required | B52: =B39*(1+$B$11)/$B$23*$B$25*$B$26 -> 850.22135 | C52: =C39*(1+$B$11)/$B$23*$B$25*$B$26 -> 2805.7305 | D52: =D39*(1+$B$11)/$B$23*$B$25*$B$26 -> 5611.4609 | E52: =E39*(1+$B$11)/$B$23*$B$25*$B$26 -> 8502.2135 | F52: =F39*(1+$B$11)/$B$23*$B$25*$B$26 -> 8502.2135 | G52: =G39*(1+$B$11)/$B$23*$B$25*$B$26 -> 8502.2135 | H52: =H39*(1+$B$11)/$B$23*$B$25*$B$26 -> 8502.2135 | I52: =I39*(1+$B$11)/$B$23*$B$25*$B$26 -> 8502.2135 | ... AK52: =AK39*(1+$B$11)/$B$23*$B$25*$B$26 -> 8502.2135
A53: Total Expenses | B53: =SUM(B49:B52) -> 12100.221 | C53: =SUM(C49:C52) -> 12680.73 | D53: =SUM(D49:D52) -> 15303.128 | E53: =SUM(E49:E52) -> 19752.214 | F53: =SUM(F49:F52) -> 19752.214 | G53: =SUM(G49:G52) -> 19752.214 | H53: =SUM(H49:H52) -> 19752.214 | I53: =SUM(I49:I52) -> 19752.214 | ... AK53: =SUM(AK49:AK52) -> 19752.214
A54: Cumulative expenses | B54: =B53 -> 12100.221 | C54: =C53+B54 -> 24780.952 | D54: =D53+C54 -> 40084.079 | E54: =E53+D54 -> 59836.293 | F54: =F53+E54 -> 79588.507 | G54: =G53+F54 -> 99340.72 | H54: =H53+G54 -> 119092.93 | I54: =I53+H54 -> 138845.15 | J54: =J53+I54 -> 158597.36 | ... AK54: =AK53+AJ54 -> 691907.13
A56: Breakeven Analysis | B56: Month 1 | C56: Month 2 | D56: Month 3 | E56: Month 4 | F56: Month 5 | G56: Month 6 | H56: Month 7 | I56: Month 8 | J56: Month 9 | K56: Month 10 | L56: Month 11 | M56: Month 12 | N56: Month 13 | O56: Month 14 | P56: Month 15 | Q56: Month 16 | R56: Month 17 | S56: Month 18 | T56: Month 19 | U56: Month 20 | V56: Month 21 | W56: Month 22 | X56: Month 23 | Y56: Month 24 | Z56: Month 25 | AA56: Month 26 | AB56: Month 27 | AC56: Month 28 | AD56: Month 29 | AE56: Month 30 | AF56: Month 31 | AG56: Month 32 | AH56: Month 33 | AI56: Month 34 | AJ56: Month 35 | AK56: Month 36
A57: Net profit | B57: =B43*$B$20-B53 -> -11864.11 | C57: =C43*$B$20-C53 -> -11671.355 | D57: =D43*$B$20-D53 -> -12760.654 | E57: =E43*$B$20-E53 -> -14912.19 | F57: =F43*$B$20-F53 -> -12672.08 | G57: =G43*$B$20-G53 -> -10487.972 | H57: =H43*$B$20-H53 -> -8358.4669 | I57: =I43*$B$20-I53 -> -6282.1995 | ... AK57: =AK43*$B$20-AK53 -> 34837.751
A58: Cumulative Net Profit | B58: =B45-B54 -> -11864.11 | C58: =C45-C54 -> -23535.466 | D58: =D45-D54 -> -36296.119 | E58: =E45-E54 -> -51208.31 | F58: =F45-F54 -> -63880.389 | G58: =G45-G54 -> -74368.361 | H58: =H45-H54 -> -82726.828 | I58: =I45-I54 -> -89009.028 | ... AK58: =AK45-AK54 -> 398695.35
A76: Part 2: Look at the Overall Economics when Ramping Sales Hires
B78: Month 1 | C78: Month 2 | D78: Month 3 | E78: Month 4 | F78: Month 5 | G78: Month 6 | H78: Month 7 | I78: Month 8 | J78: Month 9 | K78: Month 10 | L78: Month 11 | M78: Month 12 | N78: Month 13 | O78: Month 14 | P78: Month 15 | Q78: Month 16 | R78: Month 17 | S78: Month 18 | T78: Month 19 | U78: Month 20 | V78: Month 21 | W78: Month 22 | X78: Month 23 | Y78: Month 24 | Z78: Month 25 | AA78: Month 26 | AB78: Month 27 | AC78: Month 28 | AD78: Month 29 | AE78: Month 30 | AF78: Month 31 | AG78: Month 32 | AH78: Month 33 | AI78: Month 34 | AJ78: Month 35 | AK78: Month 36
A79: New Sales Hires | B79: 2 | C79: 2 | D79: 2 | E79: 2 | F79: 2 | G79: 2 | H79: 2 | I79: 2 | J79: 2 | K79: 2 | L79: 2 | M79: 2 | N79: 2 | O79: 2 | P79: 2 | Q79: 2 | R79: 2 | S79: 2 | T79: 2 | U79: 2 | V79: 2 | W79: 2 | X79: 2 | Y79: 2 | Z79: 2 | AA79: 2 | AB79: 2 | AC79: 2 | AD79: 2 | AE79: 2 | AF79: 2 | AG79: 2 | AH79: 2 | AI79: 2 | AJ79: 2 | AK79: 2
A81: No of Salespeople at
A82: each stage in lifecycle | B82: Month 1 | C82: Month 2 | D82: Month 3 | E82: Month 4 | F82: Month 5 | G82: Month 6 | H82: Month 7 | I82: Month 8 | J82: Month 9 | K82: Month 10 | L82: Month 11 | M82: Month 12 | N82: Month 13 | O82: Month 14 | P82: Month 15 | Q82: Month 16 | R82: Month 17 | S82: Month 18 | T82: Month 19 | U82: Month 20 | V82: Month 21 | W82: Month 22 | X82: Month 23 | Y82: Month 24 | Z82: Month 25 | AA82: Month 26 | AB82: Month 27 | AC82: Month 28 | AD82: Month 29 | AE82: Month 30 | AF82: Month 31 | AG82: Month 32 | AH82: Month 33 | AI82: Month 34 | AJ82: Month 35 | AK82: Month 36
A83: 1st month | B83: =B79 -> 2 | C83: =C79 -> 2 | D83: =D79 -> 2 | E83: =E79 -> 2 | F83: =F79 -> 2 | G83: =G79 -> 2 | H83: =H79 -> 2 | I83: =I79 -> 2 | ... AK83: =AK79 -> 2
A84: 2nd month | C84: =B83 -> 2 | D84: =C83 -> 2 | E84: =D83 -> 2 | F84: =E83 -> 2 | G84: =F83 -> 2 | H84: =G83 -> 2 | I84: =H83 -> 2 | J84: =I83 -> 2 | ... AK84: =AJ83 -> 2
A85: 3rd month | D85: =C84 -> 2 | E85: =D84 -> 2 | F85: =E84 -> 2 | G85: =F84 -> 2 | H85: =G84 -> 2 | I85: =H84 -> 2 | J85: =I84 -> 2 | K85: =J84 -> 2 | ... AK85: =AJ84 -> 2
A86: 4th month | E86: =D85 -> 2 | F86: =E85 -> 2 | G86: =F85 -> 2 | H86: =G85 -> 2 | I86: =H85 -> 2 | J86: =I85 -> 2 | K86: =J85 -> 2 | L86: =K85 -> 2 | ... AK86: =AJ85 -> 2
A87: 5th month | F87: =E86 -> 2 | G87: =F86 -> 2 | H87: =G86 -> 2 | I87: =H86 -> 2 | J87: =I86 -> 2 | K87: =J86 -> 2 | L87: =K86 -> 2 | M87: =L86 -> 2 | ... AK87: =AJ86 -> 2
A88: 6th month | G88: =F87 -> 2 | H88: =G87 -> 2 | I88: =H87 -> 2 | J88: =I87 -> 2 | K88: =J87 -> 2 | L88: =K87 -> 2 | M88: =L87 -> 2 | N88: =M87 -> 2 | ... AK88: =AJ87 -> 2
A89: 7th month | H89: =G88 -> 2 | I89: =H88 -> 2 | J89: =I88 -> 2 | K89: =J88 -> 2 | L89: =K88 -> 2 | M89: =L88 -> 2 | N89: =M88 -> 2 | O89: =N88 -> 2 | ... AK89: =AJ88 -> 2
A90: 4th month | I90: =H89 -> 2 | J90: =I89 -> 2 | K90: =J89 -> 2 | L90: =K89 -> 2 | M90: =L89 -> 2 | N90: =M89 -> 2 | O90: =N89 -> 2 | P90: =O89 -> 2 | ... AK90: =AJ89 -> 2
A91: 4th month | J91: =I90 -> 2 | K91: =J90 -> 2 | L91: =K90 -> 2 | M91: =L90 -> 2 | N91: =M90 -> 2 | O91: =N90 -> 2 | P91: =O90 -> 2 | Q91: =P90 -> 2 | ... AK91: =AJ90 -> 2
A92: 10th month & Beyond | K92: =J91 -> 2 | L92: =K92+K91 -> 4 | M92: =L92+L91 -> 6 | N92: =M92+M91 -> 8 | O92: =N92+N91 -> 10 | P92: =O92+O91 -> 12 | Q92: =P92+P91 -> 14 | R92: =Q92+Q91 -> 16 | S92: =R92+R91 -> 18 | ... AK92: =AJ92+AJ91 -> 54
A93: Total Sales Headcount | B93: =SUM(B83:B92) -> 2 | C93: =SUM(C83:C92) -> 4 | D93: =SUM(D83:D92) -> 6 | E93: =SUM(E83:E92) -> 8 | F93: =SUM(F83:F92) -> 10 | G93: =SUM(G83:G92) -> 12 | H93: =SUM(H83:H92) -> 14 | I93: =SUM(I83:I92) -> 16 | ... AK93: =SUM(AK83:AK92) -> 72
A94: Total Leads Required | B94: =B98*(1+$B$11)/$B$23*$B$25 -> 13.576389 | C94: =C98*(1+$B$11)/$B$23*$B$25 -> 58.378472 | D94: =D98*(1+$B$11)/$B$23*$B$25 -> 147.98264 | E94: =E98*(1+$B$11)/$B$23*$B$25 -> 283.74653 | F94: =F98*(1+$B$11)/$B$23*$B$25 -> 419.51042 | G94: =G98*(1+$B$11)/$B$23*$B$25 -> 555.27431 | H94: =H98*(1+$B$11)/$B$23*$B$25 -> 691.03819 | I94: =I98*(1+$B$11)/$B$23*$B$25 -> 826.80208 | ... AK94: =AK98*(1+$B$11)/$B$23*$B$25 -> 4628.191
A97: Income | B97: Month 1 | C97: Month 2 | D97: Month 3 | E97: Month 4 | F97: Month 5 | G97: Month 6 | H97: Month 7 | I97: Month 8 | J97: Month 9 | K97: Month 10 | L97: Month 11 | M97: Month 12 | N97: Month 13 | O97: Month 14 | P97: Month 15 | Q97: Month 16 | R97: Month 17 | S97: Month 18 | T97: Month 19 | U97: Month 20 | V97: Month 21 | W97: Month 22 | X97: Month 23 | Y97: Month 24 | Z97: Month 25 | AA97: Month 26 | AB97: Month 27 | AC97: Month 28 | AD97: Month 29 | AE97: Month 30 | AF97: Month 31 | AG97: Month 32 | AH97: Month 33 | AI97: Month 34 | AJ97: Month 35 | AK97: Month 36
A98: Bookings (ACV) | B98: =B$83*$B39+B$84*$C39+B$85*$D39+B$86*$E39+B$87*$F39+B$88*$G39+B$89*$H39+B$90*$I39+B$91*$J39+B$92*$K39 -> 7083.3333 | C98: =C$83*$B39+C$84*$C39+C$85*$D39+C$86*$E39+C$87*$F39+C$88*$G39+C$89*$H39+C$90*$I39+C$91*$J39+C$92*$K39 -> 30458.333 | D98: =D$83*$B39+D$84*$C39+D$85*$D39+D$86*$E39+D$87*$F39+D$88*$G39+D$89*$H39+D$90*$I39+D$91*$J39+D$92*$K39 -> 77208.333 | E98: =E$83*$B39+E$84*$C39+E$85*$D39+E$86*$E39+E$87*$F39+E$88*$G39+E$89*$H39+E$90*$I39+E$91*$J39+E$92*$K39 -> 148041.67 | F98: =F$83*$B39+F$84*$C39+F$85*$D39+F$86*$E39+F$87*$F39+F$88*$G39+F$89*$H39+F$90*$I39+F$91*$J39+F$92*$K39 -> 218875 | G98: =G$83*$B39+G$84*$C39+G$85*$D39+G$86*$E39+G$87*$F39+G$88*$G39+G$89*$H39+G$90*$I39+G$91*$J39+G$92*$K39 -> 289708.33 | H98: =H$83*$B39+H$84*$C39+H$85*$D39+H$86*$E39+H$87*$F39+H$88*$G39+H$89*$H39+H$90*$I39+H$91*$J39+H$92*$K39 -> 360541.67 | I98: =I$83*$B39+I$84*$C39+I$85*$D39+I$86*$E39+I$87*$F39+I$88*$G39+I$89*$H39+I$90*$I39+I$91*$J39+I$92*$K39 -> 431375 | ... AK98: =AK$83*$B39+AK$84*$C39+AK$85*$D39+AK$86*$E39+AK$87*$F39+AK$88*$G39+AK$89*$H39+AK$90*$I39+AK$91*$J39+AK$92*$K39 -> 2414708.3
A99: Total MRR (Billings) | B99: =B98/12 -> 590.27778 | C99: =C98/12+B99*(1-$B$19) -> 3113.7153 | D99: =D98/12+C99*(1-$B$19) -> 9469.9002 | E99: =E98/12+D99*(1-$B$19) -> 21569.958 | F99: =F98/12+E99*(1-$B$19) -> 39270.293 | G99: =G98/12+F99*(1-$B$19) -> 62430.896 | H99: =H98/12+G99*(1-$B$19) -> 90915.263 | I99: =I98/12+H99*(1-$B$19) -> 124590.3 | J99: =J98/12+I99*(1-$B$19) -> 163326.23 | ... AK99: =AK98/12+AJ99*(1-$B$19) -> 2726506.2
A100: Cumulative Billings | B100: =B99 -> 590.27778 | C100: =B100+C99 -> 3703.9931 | D100: =C100+D99 -> 13173.893 | E100: =D100+E99 -> 34743.851 | F100: =E100+F99 -> 74014.144 | G100: =F100+G99 -> 136445.04 | H100: =G100+H99 -> 227360.3 | I100: =H100+I99 -> 351950.6 | J100: =I100+J99 -> 515276.84 | ... AK100: =AJ100+AK99 -> 35000008
A101: Cumulative Gross Profit | B101: =$B$20*B100 -> 472.22222 | C101: =$B$20*C100 -> 2963.1944 | D101: =$B$20*D100 -> 10539.115 | E101: =$B$20*E100 -> 27795.081 | F101: =$B$20*F100 -> 59211.315 | G101: =$B$20*G100 -> 109156.03 | H101: =$B$20*H100 -> 181888.24 | I101: =$B$20*I100 -> 281560.48 | ... AK101: =$B$20*AK100 -> 28000007
A102: Growth in MRR | B102: =B99 -> 590.27778 | C102: =C99-B99 -> 2523.4375 | D102: =D99-C99 -> 6356.1849 | E102: =E99-D99 -> 12100.058 | F102: =F99-E99 -> 17700.334 | G102: =G99-F99 -> 23160.604 | H102: =H99-G99 -> 28484.366 | I102: =I99-H99 -> 33675.035 | J102: =J99-I99 -> 38735.937 | ... AK102: =AK99-AJ99 -> 136474.91
A104: Expenses
A105: Base Salary | B105: =B$93*B49 -> 8333.3333 | C105: =C$93*C49 -> 16666.667 | D105: =D$93*D49 -> 25000 | E105: =E$93*E49 -> 33333.333 | F105: =F$93*F49 -> 41666.667 | G105: =G$93*G49 -> 50000 | H105: =H$93*H49 -> 58333.333 | I105: =I$93*I49 -> 66666.667 | ... AK105: =AK$93*AK49 -> 300000
A106: Variable Compensation | B106: =B$83*$B50+B$84*$C50+B$85*$D50+B$86*$E50+B$87*$F50+B$88*$G50+B$89*$H50+B$90*$I50+B$91*$J50+B$92*$K50 -> 9166.6667 | C106: =C$83*$B50+C$84*$C50+C$85*$D50+C$86*$E50+C$87*$F50+C$88*$G50+C$89*$H50+C$90*$I50+C$91*$J50+C$92*$K50 -> 15583.333 | D106: =D$83*$B50+D$84*$C50+D$85*$D50+D$86*$E50+D$87*$F50+D$88*$G50+D$89*$H50+D$90*$I50+D$91*$J50+D$92*$K50 -> 21633.333 | E106: =E$83*$B50+E$84*$C50+E$85*$D50+E$86*$E50+E$87*$F50+E$88*$G50+E$89*$H50+E$90*$I50+E$91*$J50+E$92*$K50 -> 30800 | F106: =F$83*$B50+F$84*$C50+F$85*$D50+F$86*$E50+F$87*$F50+F$88*$G50+F$89*$H50+F$90*$I50+F$91*$J50+F$92*$K50 -> 39966.667 | G106: =G$83*$B50+G$84*$C50+G$85*$D50+G$86*$E50+G$87*$F50+G$88*$G50+G$89*$H50+G$90*$I50+G$91*$J50+G$92*$K50 -> 49133.333 | H106: =H$83*$B50+H$84*$C50+H$85*$D50+H$86*$E50+H$87*$F50+H$88*$G50+H$89*$H50+H$90*$I50+H$91*$J50+H$92*$K50 -> 58300 | I106: =I$83*$B50+I$84*$C50+I$85*$D50+I$86*$E50+I$87*$F50+I$88*$G50+I$89*$H50+I$90*$I50+I$91*$J50+I$92*$K50 -> 67466.667 | ... AK106: =AK$83*$B50+AK$84*$C50+AK$85*$D50+AK$86*$E50+AK$87*$F50+AK$88*$G50+AK$89*$H50+AK$90*$I50+AK$91*$J50+AK$92*$K50 -> 324133.33
A107: Overhead | B107: =B$93*B51 -> 5000 | C107: =C$93*C51 -> 10000 | D107: =D$93*D51 -> 15000 | E107: =E$93*E51 -> 20000 | F107: =F$93*F51 -> 25000 | G107: =G$93*G51 -> 30000 | H107: =H$93*H51 -> 35000 | I107: =I$93*I51 -> 40000 | ... AK107: =AK$93*AK51 -> 180000
A108: Cost of leads required | B108: =B94*$B$26 -> 1700.4427 | C108: =C94*$B$26 -> 7311.9036 | D108: =D94*$B$26 -> 18534.826 | E108: =E94*$B$26 -> 35539.253 | F108: =F94*$B$26 -> 52543.68 | G108: =G94*$B$26 -> 69548.107 | H108: =H94*$B$26 -> 86552.534 | I108: =I94*$B$26 -> 103556.96 | ... AK108: =AK94*$B$26 -> 579680.92
A109: Total Expenses | B109: =SUM(B105:B108) -> 24200.443 | C109: =SUM(C105:C108) -> 49561.904 | D109: =SUM(D105:D108) -> 80168.159 | E109: =SUM(E105:E108) -> 119672.59 | F109: =SUM(F105:F108) -> 159177.01 | G109: =SUM(G105:G108) -> 198681.44 | H109: =SUM(H105:H108) -> 238185.87 | I109: =SUM(I105:I108) -> 277690.29 | ... AK109: =SUM(AK105:AK108) -> 1383814.3
A110: Cumulative expenses | B110: =B109 -> 24200.443 | C110: =C109+B110 -> 73762.346 | D110: =D109+C110 -> 153930.51 | E110: =E109+D110 -> 273603.09 | F110: =F109+E110 -> 432780.1 | G110: =G109+F110 -> 631461.54 | H110: =H109+G110 -> 869647.41 | I110: =I109+H110 -> 1147337.7 | J110: =J109+I110 -> 1464532.4 | ... AK110: =AK109+AJ110 -> 24961463
A112: Breakeven Analysis | B112: Month 1 | C112: Month 2 | D112: Month 3 | E112: Month 4 | F112: Month 5 | G112: Month 6 | H112: Month 7 | I112: Month 8 | J112: Month 9 | K112: Month 10 | L112: Month 11 | M112: Month 12 | N112: Month 13 | O112: Month 14 | P112: Month 15 | Q112: Month 16 | R112: Month 17 | S112: Month 18 | T112: Month 19 | U112: Month 20 | V112: Month 21 | W112: Month 22 | X112: Month 23 | Y112: Month 24 | Z112: Month 25 | AA112: Month 26 | AB112: Month 27 | AC112: Month 28 | AD112: Month 29 | AE112: Month 30 | AF112: Month 31 | AG112: Month 32 | AH112: Month 33 | AI112: Month 34 | AJ112: Month 35 | AK112: Month 36
A113: Net profit | B113: =B99*$B$20-B109 -> -23728.22 | C113: =C99*$B$20-C109 -> -47070.931 | D113: =D99*$B$20-D109 -> -72592.239 | E113: =E99*$B$20-E109 -> -102416.62 | F113: =F99*$B$20-F109 -> -127760.78 | G113: =G99*$B$20-G109 -> -148736.72 | H113: =H99*$B$20-H109 -> -165453.66 | I113: =I99*$B$20-I109 -> -178018.06 | ... AK113: =AK99*$B$20-AK109 -> 797390.7
A114: Cumulative Net Profit | B114: =B101-B110 -> -23728.22 | C114: =C101-C110 -> -70799.152 | D114: =D101-D110 -> -143391.39 | E114: =E101-E110 -> -245808.01 | F114: =F101-F110 -> -373568.79 | G114: =G101-G110 -> -522305.51 | H114: =H101-H110 -> -687759.17 | I114: =I101-I110 -> -865777.22 | ... AK114: =AK101-AK110 -> 3038543.4
A149: Part 3: Look at the impact of collecting 1 year's payment in advance
A151: Step 1: Individual Sales person
A152: Income | B152: Month 1 | C152: Month 2 | D152: Month 3 | E152: Month 4 | F152: Month 5 | G152: Month 6 | H152: Month 7 | I152: Month 8 | J152: Month 9 | K152: Month 10 | L152: Month 11 | M152: Month 12 | N152: Month 13 | O152: Month 14 | P152: Month 15 | Q152: Month 16 | R152: Month 17 | S152: Month 18 | T152: Month 19 | U152: Month 20 | V152: Month 21 | W152: Month 22 | X152: Month 23 | Y152: Month 24 | Z152: Month 25 | AA152: Month 26 | AB152: Month 27 | AC152: Month 28 | AD152: Month 29 | AE152: Month 30 | AF152: Month 31 | AG152: Month 32 | AH152: Month 33 | AI152: Month 34 | AJ152: Month 35 | AK152: Month 36
A153: Productivity Ramp | B153: 0.1 | C153: 0.33 | D153: 0.66 | E153: 1 | F153: 1 | G153: 1 | H153: 1 | I153: 1 | J153: 1 | K153: 1 | L153: 1 | M153: 1 | N153: 1 | O153: 1 | P153: 1 | Q153: 1 | R153: 1 | S153: 1 | T153: 1 | U153: 1 | V153: 1 | W153: 1 | X153: 1 | Y153: 1 | Z153: 1 | AA153: 1 | AB153: 1 | AC153: 1 | AD153: 1 | AE153: 1 | AF153: 1 | AG153: 1 | AH153: 1 | AI153: 1 | AJ153: 1 | AK153: 1
A154: Bookings (ACV) | B154: =B153*$B$15*(1-$B$11) -> 3541.6667 | C154: =C153*$B$15*(1-$B$11) -> 11687.5 | D154: =D153*$B$15*(1-$B$11) -> 23375 | E154: =E153*$B$15*(1-$B$11) -> 35416.667 | F154: =F153*$B$15*(1-$B$11) -> 35416.667 | G154: =G153*$B$15*(1-$B$11) -> 35416.667 | H154: =H153*$B$15*(1-$B$11) -> 35416.667 | I154: =I153*$B$15*(1-$B$11) -> 35416.667 | ... AK154: =AK153*$B$15*(1-$B$11) -> 35416.667
A155: Renewable contract value | M155: =B154 -> 3541.6667 | N155: =C154 -> 11687.5 | O155: =D154 -> 23375 | P155: =E154 -> 35416.667 | Q155: =F154 -> 35416.667 | R155: =G154 -> 35416.667 | S155: =H154 -> 35416.667 | T155: =I154 -> 35416.667 | ... Y155: =N154 -> 35416.667 | Z155: =M154+M157 -> 37895.833 | AA155: =N154+N157 -> 43597.917 | AB155: =O154+O157 -> 51779.167 | AC155: =P154+P157 -> 60208.333 | AD155: =Q154+Q157 -> 60208.333 | AE155: =R154+R157 -> 60208.333 | AF155: =S154+S157 -> 60208.333 | AG155: =T154+T157 -> 60208.333 | ... AK155: =X154+X157 -> 60208.333
A156: Churn | M156: =-$B$19*12*M155 -> -1062.5 | N156: =-$B$19*12*N155 -> -3506.25 | O156: =-$B$19*12*O155 -> -7012.5 | P156: =-$B$19*12*P155 -> -10625 | Q156: =-$B$19*12*Q155 -> -10625 | R156: =-$B$19*12*R155 -> -10625 | S156: =-$B$19*12*S155 -> -10625 | T156: =-$B$19*12*T155 -> -10625 | ... AK156: =-$B$19*12*AK155 -> -18062.5
A157: Renewals (renewable - churn) | M157: =M155+M156 -> 2479.1667 | N157: =N155+N156 -> 8181.25 | O157: =O155+O156 -> 16362.5 | P157: =P155+P156 -> 24791.667 | Q157: =Q155+Q156 -> 24791.667 | R157: =R155+R156 -> 24791.667 | S157: =S155+S156 -> 24791.667 | T157: =T155+T156 -> 24791.667 | ... AK157: =AK155+AK156 -> 42145.833
A158: Billings (bookings + renewals) | B158: =B154 -> 3541.6667 | C158: =C154 -> 11687.5 | D158: =D154 -> 23375 | E158: =E154 -> 35416.667 | F158: =F154 -> 35416.667 | G158: =G154 -> 35416.667 | H158: =H154 -> 35416.667 | I158: =I154 -> 35416.667 | ... L158: =L154 -> 35416.667 | M158: =M154+M157 -> 37895.833 | N158: =N154+N157 -> 43597.917 | O158: =O154+O157 -> 51779.167 | P158: =P154+P157 -> 60208.333 | Q158: =Q154+Q157 -> 60208.333 | R158: =R154+R157 -> 60208.333 | S158: =S154+S157 -> 60208.333 | T158: =T154+T157 -> 60208.333 | ... AK158: =AK154+AK157 -> 77562.5
A159: Cumulative Billings | B159: =B158 -> 3541.6667 | C159: =B159+C158 -> 15229.167 | D159: =C159+D158 -> 38604.167 | E159: =D159+E158 -> 74020.833 | F159: =E159+F158 -> 109437.5 | G159: =F159+G158 -> 144854.17 | H159: =G159+H158 -> 180270.83 | I159: =H159+I158 -> 215687.5 | J159: =I159+J158 -> 251104.17 | ... AK159: =AJ159+AK158 -> 1954897.3
A160: Cumulative Gross Profit | B160: =$B$20*B159 -> 2833.3333 | C160: =$B$20*C159 -> 12183.333 | D160: =$B$20*D159 -> 30883.333 | E160: =$B$20*E159 -> 59216.667 | F160: =$B$20*F159 -> 87550 | G160: =$B$20*G159 -> 115883.33 | H160: =$B$20*H159 -> 144216.67 | I160: =$B$20*I159 -> 172550 | ... AK160: =$B$20*AK159 -> 1563917.8
A163: Breakeven Analysis | B163: Month 1 | C163: Month 2 | D163: Month 3 | E163: Month 4 | F163: Month 5 | G163: Month 6 | H163: Month 7 | I163: Month 8 | J163: Month 9 | K163: Month 10 | L163: Month 11 | M163: Month 12 | N163: Month 13 | O163: Month 14 | P163: Month 15 | Q163: Month 16 | R163: Month 17 | S163: Month 18 | T163: Month 19 | U163: Month 20 | V163: Month 21 | W163: Month 22 | X163: Month 23 | Y163: Month 24 | Z163: Month 25 | AA163: Month 26 | AB163: Month 27 | AC163: Month 28 | AD163: Month 29 | AE163: Month 30 | AF163: Month 31 | AG163: Month 32 | AH163: Month 33 | AI163: Month 34 | AJ163: Month 35 | AK163: Month 36
A164: Net Cash Flows | B164: =B158*$B$20-B53 -> -9266.888 | C164: =C158*$B$20-C53 -> -3330.7305 | D164: =D158*$B$20-D53 -> 3396.8724 | E164: =E158*$B$20-E53 -> 8581.1198 | F164: =F158*$B$20-F53 -> 8581.1198 | G164: =G158*$B$20-G53 -> 8581.1198 | H164: =H158*$B$20-H53 -> 8581.1198 | I164: =I158*$B$20-I53 -> 8581.1198 | ... AK164: =AK158*$B$20-AK53 -> 42297.786
A165: Cumulative Net Cash Flows | B165: =B160-B54 -> -9266.888 | C165: =C160-C54 -> -12597.618 | D165: =D160-D54 -> -9200.7461 | E165: =E160-E54 -> -619.6263 | F165: =F160-F54 -> 7961.4935 | G165: =G160-G54 -> 16542.613 | H165: =H160-H54 -> 25123.733 | I165: =I160-I54 -> 33704.853 | ... AK165: =AK160-AK54 -> 872010.71
A183: Step 2: Look at the Overall Economics when Ramping Sales Hires
A184: Income | B184: Month 1 | C184: Month 2 | D184: Month 3 | E184: Month 4 | F184: Month 5 | G184: Month 6 | H184: Month 7 | I184: Month 8 | J184: Month 9 | K184: Month 10 | L184: Month 11 | M184: Month 12 | N184: Month 13 | O184: Month 14 | P184: Month 15 | Q184: Month 16 | R184: Month 17 | S184: Month 18 | T184: Month 19 | U184: Month 20 | V184: Month 21 | W184: Month 22 | X184: Month 23 | Y184: Month 24 | Z184: Month 25 | AA184: Month 26 | AB184: Month 27 | AC184: Month 28 | AD184: Month 29 | AE184: Month 30 | AF184: Month 31 | AG184: Month 32 | AH184: Month 33 | AI184: Month 34 | AJ184: Month 35 | AK184: Month 36
A185: Bookings (ACV) | B185: =B98 -> 7083.3333 | C185: =C98 -> 30458.333 | D185: =D98 -> 77208.333 | E185: =E98 -> 148041.67 | F185: =F98 -> 218875 | G185: =G98 -> 289708.33 | H185: =H98 -> 360541.67 | I185: =I98 -> 431375 | ... AK185: =AK98 -> 2414708.3
A186: Billings less churn (MRR) | B186: =B185 -> 7083.3333 | C186: =C185 -> 30458.333 | D186: =D185 -> 77208.333 | E186: =E185 -> 148041.67 | F186: =F185 -> 218875 | G186: =G185 -> 289708.33 | H186: =H185 -> 360541.67 | I186: =I185 -> 431375 | ... M186: =M185 -> 714708.33 | N186: =N185+B186*12*$B$19 -> 787666.67 | O186: =O185+C186*12*$B$19 -> 865512.5 | P186: =P185+D186*12*$B$19 -> 950370.83 | Q186: =Q185+E186*12*$B$19 -> 1042454.2 | R186: =R185+F186*12*$B$19 -> 1134537.5 | S186: =S185+G186*12*$B$19 -> 1226620.8 | T186: =T185+H186*12*$B$19 -> 1318704.2 | U186: =U185+I186*12*$B$19 -> 1410787.5 | ... AK186: =AK185+Y186*12*$B$19 -> 2948444.6
...

Sheet Hiring Rate comparison
A1: Comparison of hiring 1 versus 2 sales people per month
A5: Data for hiring 1 sales person per month
B7: Month 1 | C7: Month 2 | D7: Month 3 | E7: Month 4 | F7: Month 5 | G7: Month 6 | H7: Month 7 | I7: Month 8 | J7: Month 9 | K7: Month 10 | L7: Month 11 | M7: Month 12 | N7: Month 13 | O7: Month 14 | P7: Month 15 | Q7: Month 16 | R7: Month 17 | S7: Month 18 | T7: Month 19 | U7: Month 20 | V7: Month 21 | W7: Month 22 | X7: Month 23 | Y7: Month 24 | Z7: Month 25 | AA7: Month 26 | AB7: Month 27 | AC7: Month 28 | AD7: Month 29 | AE7: Month 30 | AF7: Month 31 | AG7: Month 32 | AH7: Month 33 | AI7: Month 34 | AJ7: Month 35 | AK7: Month 36
A8: New Sales Hires | B8: 1 | C8: 1 | D8: 1 | E8: 1 | F8: 1 | G8: 1 | H8: 1 | I8: 1 | J8: 1 | K8: 1 | L8: 1 | M8: 1 | N8: 1 | O8: 1 | P8: 1 | Q8: 1 | R8: 1 | S8: 1 | T8: 1 | U8: 1 | V8: 1 | W8: 1 | X8: 1 | Y8: 1 | Z8: 1 | AA8: 1 | AB8: 1 | AC8: 1 | AD8: 1 | AE8: 1 | AF8: 1 | AG8: 1 | AH8: 1 | AI8: 1 | AJ8: 1 | AK8: 1
A10: No of Salespeople at
A11: each stage in lifecycle | B11: Month 1 | C11: Month 2 | D11: Month 3 | E11: Month 4 | F11: Month 5 | G11: Month 6 | H11: Month 7 | I11: Month 8 | J11: Month 9 | K11: Month 10 | L11: Month 11 | M11: Month 12 | N11: Month 13 | O11: Month 14 | P11: Month 15 | Q11: Month 16 | R11: Month 17 | S11: Month 18 | T11: Month 19 | U11: Month 20 | V11: Month 21 | W11: Month 22 | X11: Month 23 | Y11: Month 24 | Z11: Month 25 | AA11: Month 26 | AB11: Month 27 | AC11: Month 28 | AD11: Month 29 | AE11: Month 30 | AF11: Month 31 | AG11: Month 32 | AH11: Month 33 | AI11: Month 34 | AJ11: Month 35 | AK11: Month 36
A12: 1st month | B12: =B8 -> 1 | C12: =C8 -> 1 | D12: =D8 -> 1 | E12: =E8 -> 1 | F12: =F8 -> 1 | G12: =G8 -> 1 | H12: =H8 -> 1 | I12: =I8 -> 1 | ... AK12: =AK8 -> 1
A13: 2nd month | C13: =B12 -> 1 | D13: =C12 -> 1 | E13: =D12 -> 1 | F13: =E12 -> 1 | G13: =F12 -> 1 | H13: =G12 -> 1 | I13: =H12 -> 1 | J13: =I12 -> 1 | ... AK13: =AJ12 -> 1
A14: 3rd month | D14: =C13 -> 1 | E14: =D13 -> 1 | F14: =E13 -> 1 | G14: =F13 -> 1 | H14: =G13 -> 1 | I14: =H13 -> 1 | J14: =I13 -> 1 | K14: =J13 -> 1 | ... AK14: =AJ13 -> 1
A15: 4th month | E15: =D14 -> 1 | F15: =E14 -> 1 | G15: =F14 -> 1 | H15: =G14 -> 1 | I15: =H14 -> 1 | J15: =I14 -> 1 | K15: =J14 -> 1 | L15: =K14 -> 1 | ... AK15: =AJ14 -> 1
A16: 5th month | F16: =E15 -> 1 | G16: =F15 -> 1 | H16: =G15 -> 1 | I16: =H15 -> 1 | J16: =I15 -> 1 | K16: =J15 -> 1 | L16: =K15 -> 1 | M16: =L15 -> 1 | ... AK16: =AJ15 -> 1
A17: 6th month | G17: =F16 -> 1 | H17: =G16 -> 1 | I17: =H16 -> 1 | J17: =I16 -> 1 | K17: =J16 -> 1 | L17: =K16 -> 1 | M17: =L16 -> 1 | N17: =M16 -> 1 | ... AK17: =AJ16 -> 1
A18: 7th month | H18: =G17 -> 1 | I18: =H17 -> 1 | J18: =I17 -> 1 | K18: =J17 -> 1 | L18: =K17 -> 1 | M18: =L17 -> 1 | N18: =M17 -> 1 | O18: =N17 -> 1 | ... AK18: =AJ17 -> 1
A19: 4th month | I19: =H18 -> 1 | J19: =I18 -> 1 | K19: =J18 -> 1 | L19: =K18 -> 1 | M19: =L18 -> 1 | N19: =M18 -> 1 | O19: =N18 -> 1 | P19: =O18 -> 1 | ... AK19: =AJ18 -> 1
A20: 4th month | J20: =I19 -> 1 | K20: =J19 -> 1 | L20: =K19 -> 1 | M20: =L19 -> 1 | N20: =M19 -> 1 | O20: =N19 -> 1 | P20: =O19 -> 1 | Q20: =P19 -> 1 | ... AK20: =AJ19 -> 1
A21: 10th month & Beyond | K21: =J20 -> 1 | L21: =K21+K20 -> 2 | M21: =L21+L20 -> 3 | N21: =M21+M20 -> 4 | O21: =N21+N20 -> 5 | P21: =O21+O20 -> 6 | Q21: =P21+P20 -> 7 | R21: =Q21+Q20 -> 8 | S21: =R21+R20 -> 9 | ... AK21: =AJ21+AJ20 -> 27
A22: Total Sales Headcount | B22: =SUM(B12:B21) -> 1 | C22: =SUM(C12:C21) -> 2 | D22: =SUM(D12:D21) -> 3 | E22: =SUM(E12:E21) -> 4 | F22: =SUM(F12:F21) -> 5 | G22: =SUM(G12:G21) -> 6 | H22: =SUM(H12:H21) -> 7 | I22: =SUM(I12:I21) -> 8 | ... AK22: =SUM(AK12:AK21) -> 36
A23: Total Leads Required | B23: =B27*(1+'Sales Ramp'!$B$11)/'Sales Ramp'!$B$23*'Sales Ramp'!$B$25 -> 6.7881944 | C23: =C27*(1+'Sales Ramp'!$B$11)/'Sales Ramp'!$B$23*'Sales Ramp'!$B$25 -> 29.189236 | D23: =D27*(1+'Sales Ramp'!$B$11)/'Sales Ramp'!$B$23*'Sales Ramp'!$B$25 -> 73.991319 | E23: =E27*(1+'Sales Ramp'!$B$11)/'Sales Ramp'!$B$23*'Sales Ramp'!$B$25 -> 141.87326 | F23: =F27*(1+'Sales Ramp'!$B$11)/'Sales Ramp'!$B$23*'Sales Ramp'!$B$25 -> 209.75521 | G23: =G27*(1+'Sales Ramp'!$B$11)/'Sales Ramp'!$B$23*'Sales Ramp'!$B$25 -> 277.63715 | H23: =H27*(1+'Sales Ramp'!$B$11)/'Sales Ramp'!$B$23*'Sales Ramp'!$B$25 -> 345.5191 | I23: =I27*(1+'Sales Ramp'!$B$11)/'Sales Ramp'!$B$23*'Sales Ramp'!$B$25 -> 413.40104 | ... AK23: =AK27*(1+'Sales Ramp'!$B$11)/'Sales Ramp'!$B$23*'Sales Ramp'!$B$25 -> 2314.0955
A26: Income | B26: Month 1 | C26: Month 2 | D26: Month 3 | E26: Month 4 | F26: Month 5 | G26: Month 6 | H26: Month 7 | I26: Month 8 | J26: Month 9 | K26: Month 10 | L26: Month 11 | M26: Month 12 | N26: Month 13 | O26: Month 14 | P26: Month 15 | Q26: Month 16 | R26: Month 17 | S26: Month 18 | T26: Month 19 | U26: Month 20 | V26: Month 21 | W26: Month 22 | X26: Month 23 | Y26: Month 24 | Z26: Month 25 | AA26: Month 26 | AB26: Month 27 | AC26: Month 28 | AD26: Month 29 | AE26: Month 30 | AF26: Month 31 | AG26: Month 32 | AH26: Month 33 | AI26: Month 34 | AJ26: Month 35 | AK26: Month 36
A27: Bookings (ACV) | B27: =B$12*'Sales Ramp'!$B39+B$13*'Sales Ramp'!$C39+B$14*'Sales Ramp'!$D39+B$15*'Sales Ramp'!$E39+B$16*'Sales Ramp'!$F39+B$17*'Sales Ramp'!$G39+B$18*'Sales Ramp'!$H39+B$19*'Sales Ramp'!$I39+B$20*'Sales Ramp'!$J39+B$21*'Sales Ramp'!$K39 -> 3541.6667 | C27: =C$12*'Sales Ramp'!$B39+C$13*'Sales Ramp'!$C39+C$14*'Sales Ramp'!$D39+C$15*'Sales Ramp'!$E39+C$16*'Sales Ramp'!$F39+C$17*'Sales Ramp'!$G39+C$18*'Sales Ramp'!$H39+C$19*'Sales Ramp'!$I39+C$20*'Sales Ramp'!$J39+C$21*'Sales Ramp'!$K39 -> 15229.167 | D27: =D$12*'Sales Ramp'!$B39+D$13*'Sales Ramp'!$C39+D$14*'Sales Ramp'!$D39+D$15*'Sales Ramp'!$E39+D$16*'Sales Ramp'!$F39+D$17*'Sales Ramp'!$G39+D$18*'Sales Ramp'!$H39+D$19*'Sales Ramp'!$I39+D$20*'Sales Ramp'!$J39+D$21*'Sales Ramp'!$K39 -> 38604.167 | E27: =E$12*'Sales Ramp'!$B39+E$13*'Sales Ramp'!$C39+E$14*'Sales Ramp'!$D39+E$15*'Sales Ramp'!$E39+E$16*'Sales Ramp'!$F39+E$17*'Sales Ramp'!$G39+E$18*'Sales Ramp'!$H39+E$19*'Sales Ramp'!$I39+E$20*'Sales Ramp'!$J39+E$21*'Sales Ramp'!$K39 -> 74020.833 | F27: =F$12*'Sales Ramp'!$B39+F$13*'Sales Ramp'!$C39+F$14*'Sales Ramp'!$D39+F$15*'Sales Ramp'!$E39+F$16*'Sales Ramp'!$F39+F$17*'Sales Ramp'!$G39+F$18*'Sales Ramp'!$H39+F$19*'Sales Ramp'!$I39+F$20*'Sales Ramp'!$J39+F$21*'Sales Ramp'!$K39 -> 109437.5 | G27: =G$12*'Sales Ramp'!$B39+G$13*'Sales Ramp'!$C39+G$14*'Sales Ramp'!$D39+G$15*'Sales Ramp'!$E39+G$16*'Sales Ramp'!$F39+G$17*'Sales Ramp'!$G39+G$18*'Sales Ramp'!$H39+G$19*'Sales Ramp'!$I39+G$20*'Sales Ramp'!$J39+G$21*'Sales Ramp'!$K39 -> 144854.17 | H27: =H$12*'Sales Ramp'!$B39+H$13*'Sales Ramp'!$C39+H$14*'Sales Ramp'!$D39+H$15*'Sales Ramp'!$E39+H$16*'Sales Ramp'!$F39+H$17*'Sales Ramp'!$G39+H$18*'Sales Ramp'!$H39+H$19*'Sales Ramp'!$I39+H$20*'Sales Ramp'!$J39+H$21*'Sales Ramp'!$K39 -> 180270.83 | I27: =I$12*'Sales Ramp'!$B39+I$13*'Sales Ramp'!$C39+I$14*'Sales Ramp'!$D39+I$15*'Sales Ramp'!$E39+I$16*'Sales Ramp'!$F39+I$17*'Sales Ramp'!$G39+I$18*'Sales Ramp'!$H39+I$19*'Sales Ramp'!$I39+I$20*'Sales Ramp'!$J39+I$21*'Sales Ramp'!$K39 -> 215687.5 | ... AK27: =AK$12*'Sales Ramp'!$B39+AK$13*'Sales Ramp'!$C39+AK$14*'Sales Ramp'!$D39+AK$15*'Sales Ramp'!$E39+AK$16*'Sales Ramp'!$F39+AK$17*'Sales Ramp'!$G39+AK$18*'Sales Ramp'!$H39+AK$19*'Sales Ramp'!$I39+AK$20*'Sales Ramp'!$J39+AK$21*'Sales Ramp'!$K39 -> 1207354.2
A28: Total MRR (Billings) | B28: =B27/12 -> 295.13889 | C28: =C27/12+B28*(1-'Sales Ramp'!$B$19) -> 1556.8576 | D28: =D27/12+C28*(1-'Sales Ramp'!$B$19) -> 4734.9501 | E28: =E27/12+D28*(1-'Sales Ramp'!$B$19) -> 10784.979 | F28: =F27/12+E28*(1-'Sales Ramp'!$B$19) -> 19635.146 | G28: =G27/12+F28*(1-'Sales Ramp'!$B$19) -> 31215.448 | H28: =H27/12+G28*(1-'Sales Ramp'!$B$19) -> 45457.631 | I28: =I27/12+H28*(1-'Sales Ramp'!$B$19) -> 62295.149 | J28: =J27/12+I28*(1-'Sales Ramp'!$B$19) -> 81663.117 | ... AK28: =AK27/12+AJ28*(1-'Sales Ramp'!$B$19) -> 1363253.1
A29: Cumulative Billings | B29: =B28 -> 295.13889 | C29: =B29+C28 -> 1851.9965 | D29: =C29+D28 -> 6586.9466 | E29: =D29+E28 -> 17371.926 | F29: =E29+F28 -> 37007.072 | G29: =F29+G28 -> 68222.52 | H29: =G29+H28 -> 113680.15 | I29: =H29+I28 -> 175975.3 | J29: =I29+J28 -> 257638.42 | ... AK29: =AJ29+AK28 -> 17500004
A30: Cumulative Gross Profit | B30: ='Sales Ramp'!$B$20*B29 -> 236.11111 | C30: ='Sales Ramp'!$B$20*C29 -> 1481.5972 | D30: ='Sales Ramp'!$B$20*D29 -> 5269.5573 | E30: ='Sales Ramp'!$B$20*E29 -> 13897.541 | F30: ='Sales Ramp'!$B$20*F29 -> 29605.658 | G30: ='Sales Ramp'!$B$20*G29 -> 54578.016 | H30: ='Sales Ramp'!$B$20*H29 -> 90944.121 | I30: ='Sales Ramp'!$B$20*I29 -> 140780.24 | ... AK30: ='Sales Ramp'!$B$20*AK29 -> 14000003
A31: Growth in MRR | B31: =B28 -> 295.13889 | C31: =C28-B28 -> 1261.7188 | D31: =D28-C28 -> 3178.0924 | E31: =E28-D28 -> 6050.029 | F31: =F28-E28 -> 8850.1672 | G31: =G28-F28 -> 11580.302 | H31: =H28-G28 -> 14242.183 | I31: =I28-H28 -> 16837.518 | J31: =J28-I28 -> 19367.968 | ... AK31: =AK28-AJ28 -> 68237.456
A33: Expenses
A34: Base Salary | B34: =B$22*'Sales Ramp'!B49 -> 4166.6667 | C34: =C$22*'Sales Ramp'!C49 -> 8333.3333 | D34: =D$22*'Sales Ramp'!D49 -> 12500 | E34: =E$22*'Sales Ramp'!E49 -> 16666.667 | F34: =F$22*'Sales Ramp'!F49 -> 20833.333 | G34: =G$22*'Sales Ramp'!G49 -> 25000 | H34: =H$22*'Sales Ramp'!H49 -> 29166.667 | I34: =I$22*'Sales Ramp'!I49 -> 33333.333 | ... AK34: =AK$22*'Sales Ramp'!AK49 -> 150000
A35: Variable Compensation | B35: =B$12*'Sales Ramp'!$B50+B$13*'Sales Ramp'!$C50+B$14*'Sales Ramp'!$D50+B$15*'Sales Ramp'!$E50+B$16*'Sales Ramp'!$F50+B$17*'Sales Ramp'!$G50+B$18*'Sales Ramp'!$H50+B$19*'Sales Ramp'!$I50+B$20*'Sales Ramp'!$J50+B$21*'Sales Ramp'!$K50 -> 4583.3333 | C35: =C$12*'Sales Ramp'!$B50+C$13*'Sales Ramp'!$C50+C$14*'Sales Ramp'!$D50+C$15*'Sales Ramp'!$E50+C$16*'Sales Ramp'!$F50+C$17*'Sales Ramp'!$G50+C$18*'Sales Ramp'!$H50+C$19*'Sales Ramp'!$I50+C$20*'Sales Ramp'!$J50+C$21*'Sales Ramp'!$K50 -> 7791.6667 | D35: =D$12*'Sales Ramp'!$B50+D$13*'Sales Ramp'!$C50+D$14*'Sales Ramp'!$D50+D$15*'Sales Ramp'!$E50+D$16*'Sales Ramp'!$F50+D$17*'Sales Ramp'!$G50+D$18*'Sales Ramp'!$H50+D$19*'Sales Ramp'!$I50+D$20*'Sales Ramp'!$J50+D$21*'Sales Ramp'!$K50 -> 10816.667 | E35: =E$12*'Sales Ramp'!$B50+E$13*'Sales Ramp'!$C50+E$14*'Sales Ramp'!$D50+E$15*'Sales Ramp'!$E50+E$16*'Sales Ramp'!$F50+E$17*'Sales Ramp'!$G50+E$18*'Sales Ramp'!$H50+E$19*'Sales Ramp'!$I50+E$20*'Sales Ramp'!$J50+E$21*'Sales Ramp'!$K50 -> 15400 | F35: =F$12*'Sales Ramp'!$B50+F$13*'Sales Ramp'!$C50+F$14*'Sales Ramp'!$D50+F$15*'Sales Ramp'!$E50+F$16*'Sales Ramp'!$F50+F$17*'Sales Ramp'!$G50+F$18*'Sales Ramp'!$H50+F$19*'Sales Ramp'!$I50+F$20*'Sales Ramp'!$J50+F$21*'Sales Ramp'!$K50 -> 19983.333 | G35: =G$12*'Sales Ramp'!$B50+G$13*'Sales Ramp'!$C50+G$14*'Sales Ramp'!$D50+G$15*'Sales Ramp'!$E50+G$16*'Sales Ramp'!$F50+G$17*'Sales Ramp'!$G50+G$18*'Sales Ramp'!$H50+G$19*'Sales Ramp'!$I50+G$20*'Sales Ramp'!$J50+G$21*'Sales Ramp'!$K50 -> 24566.667 | H35: =H$12*'Sales Ramp'!$B50+H$13*'Sales Ramp'!$C50+H$14*'Sales Ramp'!$D50+H$15*'Sales Ramp'!$E50+H$16*'Sales Ramp'!$F50+H$17*'Sales Ramp'!$G50+H$18*'Sales Ramp'!$H50+H$19*'Sales Ramp'!$I50+H$20*'Sales Ramp'!$J50+H$21*'Sales Ramp'!$K50 -> 29150 | I35: =I$12*'Sales Ramp'!$B50+I$13*'Sales Ramp'!$C50+I$14*'Sales Ramp'!$D50+I$15*'Sales Ramp'!$E50+I$16*'Sales Ramp'!$F50+I$17*'Sales Ramp'!$G50+I$18*'Sales Ramp'!$H50+I$19*'Sales Ramp'!$I50+I$20*'Sales Ramp'!$J50+I$21*'Sales Ramp'!$K50 -> 33733.333 | ... AK35: =AK$12*'Sales Ramp'!$B50+AK$13*'Sales Ramp'!$C50+AK$14*'Sales Ramp'!$D50+AK$15*'Sales Ramp'!$E50+AK$16*'Sales Ramp'!$F50+AK$17*'Sales Ramp'!$G50+AK$18*'Sales Ramp'!$H50+AK$19*'Sales Ramp'!$I50+AK$20*'Sales Ramp'!$J50+AK$21*'Sales Ramp'!$K50 -> 162066.67
A36: Overhead | B36: =B$22*'Sales Ramp'!B51 -> 2500 | C36: =C$22*'Sales Ramp'!C51 -> 5000 | D36: =D$22*'Sales Ramp'!D51 -> 7500 | E36: =E$22*'Sales Ramp'!E51 -> 10000 | F36: =F$22*'Sales Ramp'!F51 -> 12500 | G36: =G$22*'Sales Ramp'!G51 -> 15000 | H36: =H$22*'Sales Ramp'!H51 -> 17500 | I36: =I$22*'Sales Ramp'!I51 -> 20000 | ... AK36: =AK$22*'Sales Ramp'!AK51 -> 90000
A37: Cost of leads required | B37: =B23*'Sales Ramp'!$B$26 -> 850.22135 | C37: =C23*'Sales Ramp'!$B$26 -> 3655.9518 | D37: =D23*'Sales Ramp'!$B$26 -> 9267.4128 | E37: =E23*'Sales Ramp'!$B$26 -> 17769.626 | F37: =F23*'Sales Ramp'!$B$26 -> 26271.84 | G37: =G23*'Sales Ramp'!$B$26 -> 34774.053 | H37: =H23*'Sales Ramp'!$B$26 -> 43276.267 | I37: =I23*'Sales Ramp'!$B$26 -> 51778.48 | ... AK37: =AK23*'Sales Ramp'!$B$26 -> 289840.46
A38: Total Expenses | B38: =SUM(B34:B37) -> 12100.221 | C38: =SUM(C34:C37) -> 24780.952 | D38: =SUM(D34:D37) -> 40084.079 | E38: =SUM(E34:E37) -> 59836.293 | F38: =SUM(F34:F37) -> 79588.507 | G38: =SUM(G34:G37) -> 99340.72 | H38: =SUM(H34:H37) -> 119092.93 | I38: =SUM(I34:I37) -> 138845.15 | ... AK38: =SUM(AK34:AK37) -> 691907.13
A39: Cumulative expenses | B39: =B38 -> 12100.221 | C39: =C38+B39 -> 36881.173 | D39: =D38+C39 -> 76965.253 | E39: =E38+D39 -> 136801.55 | F39: =F38+E39 -> 216390.05 | G39: =G38+F39 -> 315730.77 | H39: =H38+G39 -> 434823.71 | I39: =I38+H39 -> 573668.85 | J39: =J38+I39 -> 732266.21 | ... AK39: =AK38+AJ39 -> 12480732
A41: Breakeven Analysis | B41: Month 1 | C41: Month 2 | D41: Month 3 | E41: Month 4 | F41: Month 5 | G41: Month 6 | H41: Month 7 | I41: Month 8 | J41: Month 9 | K41: Month 10 | L41: Month 11 | M41: Month 12 | N41: Month 13 | O41: Month 14 | P41: Month 15 | Q41: Month 16 | R41: Month 17 | S41: Month 18 | T41: Month 19 | U41: Month 20 | V41: Month 21 | W41: Month 22 | X41: Month 23 | Y41: Month 24 | Z41: Month 25 | AA41: Month 26 | AB41: Month 27 | AC41: Month 28 | AD41: Month 29 | AE41: Month 30 | AF41: Month 31 | AG41: Month 32 | AH41: Month 33 | AI41: Month 34 | AJ41: Month 35 | AK41: Month 36
A42: Net profit | B42: =B28*'Sales Ramp'!$B$20-B38 -> -11864.11 | C42: =C28*'Sales Ramp'!$B$20-C38 -> -23535.466 | D42: =D28*'Sales Ramp'!$B$20-D38 -> -36296.119 | E42: =E28*'Sales Ramp'!$B$20-E38 -> -51208.31 | F42: =F28*'Sales Ramp'!$B$20-F38 -> -63880.389 | G42: =G28*'Sales Ramp'!$B$20-G38 -> -74368.361 | H42: =H28*'Sales Ramp'!$B$20-H38 -> -82726.828 | I42: =I28*'Sales Ramp'!$B$20-I38 -> -89009.028 | ... AK42: =AK28*'Sales Ramp'!$B$20-AK38 -> 398695.35
A43: Cumulative Net Profit | B43: =B30-B39 -> -11864.11 | C43: =C30-C39 -> -35399.576 | D43: =D30-D39 -> -71695.695 | E43: =E30-E39 -> -122904.01 | F43: =F30-F39 -> -186784.39 | G43: =G30-G39 -> -261152.76 | H43: =H30-H39 -> -343879.58 | I43: =I30-I39 -> -432888.61 | ... AK43: =AK30-AK39 -> 1519271.7
A46: Graphing Data
A48: MRR | B48: Month 1 | C48: Month 2 | D48: Month 3 | E48: Month 4 | F48: Month 5 | G48: Month 6 | H48: Month 7 | I48: Month 8 | J48: Month 9 | K48: Month 10 | L48: Month 11 | M48: Month 12 | N48: Month 13 | O48: Month 14 | P48: Month 15 | Q48: Month 16 | R48: Month 17 | S48: Month 18 | T48: Month 19 | U48: Month 20 | V48: Month 21 | W48: Month 22 | X48: Month 23 | Y48: Month 24 | Z48: Month 25 | AA48: Month 26 | AB48: Month 27 | AC48: Month 28 | AD48: Month 29 | AE48: Month 30 | AF48: Month 31 | AG48: Month 32 | AH48: Month 33 | AI48: Month 34 | AJ48: Month 35 | AK48: Month 36
A49: 1 sales hire a month | B49: =B28 -> 295.13889 | C49: =C28 -> 1556.8576 | D49: =D28 -> 4734.9501 | E49: =E28 -> 10784.979 | F49: =F28 -> 19635.146 | G49: =G28 -> 31215.448 | H49: =H28 -> 45457.631 | I49: =I28 -> 62295.149 | ... AK49: =AK28 -> 1363253.1
A50: 2 sales hires a month | B50: ='Sales Ramp'!B99 -> 590.27778 | C50: ='Sales Ramp'!C99 -> 3113.7153 | D50: ='Sales Ramp'!D99 -> 9469.9002 | E50: ='Sales Ramp'!E99 -> 21569.958 | F50: ='Sales Ramp'!F99 -> 39270.293 | G50: ='Sales Ramp'!G99 -> 62430.896 | H50: ='Sales Ramp'!H99 -> 90915.263 | I50: ='Sales Ramp'!I99 -> 124590.3 | ... AK50: ='Sales Ramp'!AK99 -> 2726506.2
A53: Growth in MRR | B53: Month 1 | C53: Month 2 | D53: Month 3 | E53: Month 4 | F53: Month 5 | G53: Month 6 | H53: Month 7 | I53: Month 8 | J53: Month 9 | K53: Month 10 | L53: Month 11 | M53: Month 12 | N53: Month 13 | O53: Month 14 | P53: Month 15 | Q53: Month 16 | R53: Month 17 | S53: Month 18 | T53: Month 19 | U53: Month 20 | V53: Month 21 | W53: Month 22 | X53: Month 23 | Y53: Month 24 | Z53: Month 25 | AA53: Month 26 | AB53: Month 27 | AC53: Month 28 | AD53: Month 29 | AE53: Month 30 | AF53: Month 31 | AG53: Month 32 | AH53: Month 33 | AI53: Month 34 | AJ53: Month 35 | AK53: Month 36
A54: 1 sales hire a month | B54: =B31 -> 295.13889 | C54: =C31 -> 1261.7188 | D54: =D31 -> 3178.0924 | E54: =E31 -> 6050.029 | F54: =F31 -> 8850.1672 | G54: =G31 -> 11580.302 | H54: =H31 -> 14242.183 | I54: =I31 -> 16837.518 | ... AK54: =AK31 -> 68237.456
A55: 2 sales hires a month | B55: ='Sales Ramp'!B102 -> 590.27778 | C55: ='Sales Ramp'!C102 -> 2523.4375 | D55: ='Sales Ramp'!D102 -> 6356.1849 | E55: ='Sales Ramp'!E102 -> 12100.058 | F55: ='Sales Ramp'!F102 -> 17700.334 | G55: ='Sales Ramp'!G102 -> 23160.604 | H55: ='Sales Ramp'!H102 -> 28484.366 | I55: ='Sales Ramp'!I102 -> 33675.035 | ... AK55: ='Sales Ramp'!AK102 -> 136474.91
A58: Net Profit | B58: Month 1 | C58: Month 2 | D58: Month 3 | E58: Month 4 | F58: Month 5 | G58: Month 6 | H58: Month 7 | I58: Month 8 | J58: Month 9 | K58: Month 10 | L58: Month 11 | M58: Month 12 | N58: Month 13 | O58: Month 14 | P58: Month 15 | Q58: Month 16 | R58: Month 17 | S58: Month 18 | T58: Month 19 | U58: Month 20 | V58: Month 21 | W58: Month 22 | X58: Month 23 | Y58: Month 24 | Z58: Month 25 | AA58: Month 26 | AB58: Month 27 | AC58: Month 28 | AD58: Month 29 | AE58: Month 30 | AF58: Month 31 | AG58: Month 32 | AH58: Month 33 | AI58: Month 34 | AJ58: Month 35 | AK58: Month 36
A59: 1 sales hire a month | B59: =B42 -> -11864.11 | C59: =C42 -> -23535.466 | D59: =D42 -> -36296.119 | E59: =E42 -> -51208.31 | F59: =F42 -> -63880.389 | G59: =G42 -> -74368.361 | H59: =H42 -> -82726.828 | I59: =I42 -> -89009.028 | ... AK59: =AK42 -> 398695.35
A60: 2 sales hires a month | B60: ='Sales Ramp'!B113 -> -23728.22 | C60: ='Sales Ramp'!C113 -> -47070.931 | D60: ='Sales Ramp'!D113 -> -72592.239 | E60: ='Sales Ramp'!E113 -> -102416.62 | F60: ='Sales Ramp'!F113 -> -127760.78 | G60: ='Sales Ramp'!G113 -> -148736.72 | H60: ='Sales Ramp'!H113 -> -165453.66 | I60: ='Sales Ramp'!I113 -> -178018.06 | ... AK60: ='Sales Ramp'!AK113 -> 797390.7
A63: Cumulative Net Profit | B63: Month 1 | C63: Month 2 | D63: Month 3 | E63: Month 4 | F63: Month 5 | G63: Month 6 | H63: Month 7 | I63: Month 8 | J63: Month 9 | K63: Month 10 | L63: Month 11 | M63: Month 12 | N63: Month 13 | O63: Month 14 | P63: Month 15 | Q63: Month 16 | R63: Month 17 | S63: Month 18 | T63: Month 19 | U63: Month 20 | V63: Month 21 | W63: Month 22 | X63: Month 23 | Y63: Month 24 | Z63: Month 25 | AA63: Month 26 | AB63: Month 27 | AC63: Month 28 | AD63: Month 29 | AE63: Month 30 | AF63: Month 31 | AG63: Month 32 | AH63: Month 33 | AI63: Month 34 | AJ63: Month 35 | AK63: Month 36
A64: 1 sales hire a month | B64: =B43 -> -11864.11 | C64: =C43 -> -35399.576 | D64: =D43 -> -71695.695 | E64: =E43 -> -122904.01 | F64: =F43 -> -186784.39 | G64: =G43 -> -261152.76 | H64: =H43 -> -343879.58 | I64: =I43 -> -432888.61 | ... AK64: =AK43 -> 1519271.7
A65: 2 sales hires a month | B65: ='Sales Ramp'!B114 -> -23728.22 | C65: ='Sales Ramp'!C114 -> -70799.152 | D65: ='Sales Ramp'!D114 -> -143391.39 | E65: ='Sales Ramp'!E114 -> -245808.01 | F65: ='Sales Ramp'!F114 -> -373568.79 | G65: ='Sales Ramp'!G114 -> -522305.51 | H65: ='Sales Ramp'!H114 -> -687759.17 | I65: ='Sales Ramp'!I114 -> -865777.22 | ... AK65: ='Sales Ramp'!AK114 -> 3038543.4

Sheet Churn Rate Comparison
A1: Churn Rate Comparison
A3: This is simply a copy of the first tab, with a different churn rate (1.25% versus 2.5%)
A5: Net Profit | B5: Month 1 | C5: Month 2 | D5: Month 3 | E5: Month 4 | F5: Month 5 | G5: Month 6 | H5: Month 7 | I5: Month 8 | J5: Month 9 | K5: Month 10 | L5: Month 11 | M5: Month 12 | N5: Month 13 | O5: Month 14 | P5: Month 15 | Q5: Month 16 | R5: Month 17 | S5: Month 18 | T5: Month 19 | U5: Month 20 | V5: Month 21 | W5: Month 22 | X5: Month 23 | Y5: Month 24 | Z5: Month 25 | AA5: Month 26 | AB5: Month 27 | AC5: Month 28 | AD5: Month 29 | AE5: Month 30 | AF5: Month 31 | AG5: Month 32 | AH5: Month 33 | AI5: Month 34 | AJ5: Month 35 | AK5: Month 36
A6: Churn 1.25% | B6: =B141 -> -23728.22 | C6: =C141 -> -47065.029 | D6: =D141 -> -72555.273 | E6: =E141 -> -102285.42 | F6: =F141 -> -127415.52 | G6: =G141 -> -148003.07 | H6: =H141 -> -164104.87 | I6: =I141 -> -175776.98 | ... AK6: =AK141 -> 1088847.9
A7: Churn 2.5% | B7: ='Sales Ramp'!B113 -> -23728.22 | C7: ='Sales Ramp'!C113 -> -47070.931 | D7: ='Sales Ramp'!D113 -> -72592.239 | E7: ='Sales Ramp'!E113 -> -102416.62 | F7: ='Sales Ramp'!F113 -> -127760.78 | G7: ='Sales Ramp'!G113 -> -148736.72 | H7: ='Sales Ramp'!H113 -> -165453.66 | I7: ='Sales Ramp'!I113 -> -178018.06 | ... AK7: ='Sales Ramp'!AK113 -> 797390.7
A10: Cumulative Net Profit | B10: Month 1 | C10: Month 2 | D10: Month 3 | E10: Month 4 | F10: Month 5 | G10: Month 6 | H10: Month 7 | I10: Month 8 | J10: Month 9 | K10: Month 10 | L10: Month 11 | M10: Month 12 | N10: Month 13 | O10: Month 14 | P10: Month 15 | Q10: Month 16 | R10: Month 17 | S10: Month 18 | T10: Month 19 | U10: Month 20 | V10: Month 21 | W10: Month 22 | X10: Month 23 | Y10: Month 24 | Z10: Month 25 | AA10: Month 26 | AB10: Month 27 | AC10: Month 28 | AD10: Month 29 | AE10: Month 30 | AF10: Month 31 | AG10: Month 32 | AH10: Month 33 | AI10: Month 34 | AJ10: Month 35 | AK10: Month 36
A11: Churn 1.25% | B11: =B142 -> -23728.22 | C11: =C142 -> -70793.249 | D11: =D142 -> -143348.52 | E11: =E142 -> -245633.94 | F11: =F142 -> -373049.45 | G11: =G142 -> -521052.53 | H11: =H142 -> -685157.4 | I11: =I142 -> -860934.37 | ... AK11: =AK142 -> 5832227.6
A12: Churn 2.5% | B12: ='Sales Ramp'!B114 -> -23728.22 | C12: ='Sales Ramp'!C114 -> -70799.152 | D12: ='Sales Ramp'!D114 -> -143391.39 | E12: ='Sales Ramp'!E114 -> -245808.01 | F12: ='Sales Ramp'!F114 -> -373568.79 | G12: ='Sales Ramp'!G114 -> -522305.51 | H12: ='Sales Ramp'!H114 -> -687759.17 | I12: ='Sales Ramp'!I114 -> -865777.22 | ... AK12: ='Sales Ramp'!AK114 -> 3038543.4
H32: Cells formated like this: | J32: are input variables
A34: Part 1: Model the ecomomics of a single sales person
A35: Sales compensation and overhead
A36: Base Compensation | B36: 50000
A37: Variable Compensation | B37: 55000 | C37: with 50% draw for first four months
A38: Draw on Variable Comp | B38: 1 | C38: 0.7 | D38: 0.3 | E38: 0 | F38: 0 | G38: 0 | H38: 0 | I38: 0 | J38: 0
A39: Additional overhead | B39: 30000
A40: Sales attrition factor | B40: 0.15 | C40: a factor to discount bookings to account for failed sales hires and attrition
A42: On target annual bookings
A43: Annual Bookings | B43: 500000 | C43: ACV (Annual Contract Value) | K43: Quick Marketing Calculation
A44: Monthly Bookings | B44: =B43/12 -> 41666.667 | K44: 0.5 | L44: amount of traffic that is organic versus paid
K45: 1.5 | L45: cost per paid visitor (Google AdWords, etc.)
A46: Churn Rate and Margin | K46: =K45*(1-K44) -> 0.75 | L46: Cost per visitor (both paid and unpaid)
A47: Churn Rate (monthly) | B47: 0.0125 | K47: 0.03 | L47: visitors convert to raw leads
A48: Gross Margin | B48: 0.8 | K48: 0.2 | L48: number of raw leads that turn into qualified leads
A50: Cost of Leads required to feed sales
A51: Average Deal Size | B51: 6000 | C51: (ACV) Annual Contract Value | K51: 1 | L51: qualified lead
A52: Deals to meet target | B52: =B44/B51 -> 6.9444444 | C52: per month | K52: =K51/K48 -> 5 | L52: raw leads required
A53: Leads to closed deal | B53: 10 | K53: =ROUND(K52/K47,0) -> 167 | L53: visitors required
A54: Cost per Qualified Lead | B54: =K54 -> 125.25 | K54: =K53*K46 -> 125.25 | L54: Cost of visitors (also = Cost per qualified lead)
A55: Cost of Leads required | B55: =B54*B52*B53 -> 8697.9167 | C55: per month, for 1 fully productive sales person
A58: Other interesting Calculations
A59: Lead Gen costs per deal | B59: =B54*B53 -> 1252.5 | C59: Excludes people costs
A60: Selling costs per deal | B60: =(B36+B37+B39)/12/B52 -> 1620 | C60: Excludes cost of sales management
A61: Total CAC | B61: =B60+B59 -> 2872.5 | C61: Excludes people costs in marketing, and sales management. (CAC= Cost to Acquire a Customer)
A62: Total LTV | B62: =B51*B48/12/B47 -> 32000 | C62: Calculated by dividing average monthly gross profit per customer (ARPU x Gross Margin ) by the churn rate
A65: Income | B65: Month 1 | C65: Month 2 | D65: Month 3 | E65: Month 4 | F65: Month 5 | G65: Month 6 | H65: Month 7 | I65: Month 8 | J65: Month 9 | K65: Month 10 | L65: Month 11 | M65: Month 12 | N65: Month 13 | O65: Month 14 | P65: Month 15 | Q65: Month 16 | R65: Month 17 | S65: Month 18 | T65: Month 19 | U65: Month 20 | V65: Month 21 | W65: Month 22 | X65: Month 23 | Y65: Month 24 | Z65: Month 25 | AA65: Month 26 | AB65: Month 27 | AC65: Month 28 | AD65: Month 29 | AE65: Month 30 | AF65: Month 31 | AG65: Month 32 | AH65: Month 33 | AI65: Month 34 | AJ65: Month 35 | AK65: Month 36
A66: Productivity Ramp | B66: 0.1 | C66: 0.33 | D66: 0.66 | E66: 1 | F66: 1 | G66: 1 | H66: 1 | I66: 1 | J66: 1 | K66: 1 | L66: 1 | M66: 1 | N66: 1 | O66: 1 | P66: 1 | Q66: 1 | R66: 1 | S66: 1 | T66: 1 | U66: 1 | V66: 1 | W66: 1 | X66: 1 | Y66: 1 | Z66: 1 | AA66: 1 | AB66: 1 | AC66: 1 | AD66: 1 | AE66: 1 | AF66: 1 | AG66: 1 | AH66: 1 | AI66: 1 | AJ66: 1 | AK66: 1
A67: Bookings (ACV) | B67: =B66*$B$44*(1-$B$40) -> 3541.6667 | C67: =C66*$B$44*(1-$B$40) -> 11687.5 | D67: =D66*$B$44*(1-$B$40) -> 23375 | E67: =E66*$B$44*(1-$B$40) -> 35416.667 | F67: =F66*$B$44*(1-$B$40) -> 35416.667 | G67: =G66*$B$44*(1-$B$40) -> 35416.667 | H67: =H66*$B$44*(1-$B$40) -> 35416.667 | I67: =I66*$B$44*(1-$B$40) -> 35416.667 | ... AK67: =AK66*$B$44*(1-$B$40) -> 35416.667
A68: New MRR added this month | B68: =B67/12 -> 295.13889 | C68: =C67/12 -> 973.95833 | D68: =D67/12 -> 1947.9167 | E68: =E67/12 -> 2951.3889 | F68: =F67/12 -> 2951.3889 | G68: =G67/12 -> 2951.3889 | H68: =H67/12 -> 2951.3889 | I68: =I67/12 -> 2951.3889 | ... AK68: =AK67/12 -> 2951.3889
A69: MRR from prior months bookings | C69: =B68 -> 295.13889 | D69: =C68+C69+C70 -> 1265.408 | E69: =D68+D69+D70 -> 3197.5071 | F69: =E68+E69+E70 -> 6108.9271 | G69: =F68+F69+F70 -> 8983.9544 | H69: =G68+G69+G70 -> 11823.044 | I69: =H68+H69+H70 -> 14626.645 | J69: =I68+I69+I70 -> 17395.201 | K69: =J68+J69+J70 -> 20129.149 | ... AK69: =AJ68+AJ69+AJ70 -> 80377.558
A70: Churn | C70: =-$B$47*C69 -> -3.6892361 | D70: =-$B$47*D69 -> -15.8176 | E70: =-$B$47*E69 -> -39.968838 | F70: =-$B$47*F69 -> -76.361589 | G70: =-$B$47*G69 -> -112.29943 | H70: =-$B$47*H69 -> -147.78805 | I70: =-$B$47*I69 -> -182.83306 | J70: =-$B$47*J69 -> -217.44001 | ... AK70: =-$B$47*AK69 -> -1004.7195
A71: Total MRR (Billings) | B71: =SUM(B68:B70) -> 295.13889 | C71: =SUM(C68:C70) -> 1265.408 | D71: =SUM(D68:D70) -> 3197.5071 | E71: =SUM(E68:E70) -> 6108.9271 | F71: =SUM(F68:F70) -> 8983.9544 | G71: =SUM(G68:G70) -> 11823.044 | H71: =SUM(H68:H70) -> 14626.645 | I71: =SUM(I68:I70) -> 17395.201 | ... AK71: =SUM(AK68:AK70) -> 82324.227
A72: Cumulative Billings | B72: =B71 -> 295.13889 | C72: =B72+C71 -> 1560.5469 | D72: =C72+D71 -> 4758.0539 | E72: =D72+E71 -> 10866.981 | F72: =E72+F71 -> 19850.935 | G72: =F72+G71 -> 31673.979 | H72: =G72+H71 -> 46300.624 | I72: =H72+I71 -> 63695.825 | J72: =I72+J71 -> 83824.974 | ... AK72: =AJ72+AK71 -> 1545413.8
A73: Cumulative Gross Profit | B73: =$B$48*B72 -> 236.11111 | C73: =$B$48*C72 -> 1248.4375 | D73: =$B$48*D72 -> 3806.4431 | E73: =$B$48*E72 -> 8693.5848 | F73: =$B$48*F72 -> 15880.748 | G73: =$B$48*G72 -> 25339.183 | H73: =$B$48*H72 -> 37040.499 | I73: =$B$48*I72 -> 50956.66 | ... AK73: =$B$48*AK72 -> 1236331.1
A76: Expenses
A77: Base Salary | B77: =$B$36/12 -> 4166.6667 | C77: =$B$36/12 -> 4166.6667 | D77: =$B$36/12 -> 4166.6667 | E77: =$B$36/12 -> 4166.6667 | F77: =$B$36/12 -> 4166.6667 | G77: =$B$36/12 -> 4166.6667 | H77: =$B$36/12 -> 4166.6667 | I77: =$B$36/12 -> 4166.6667 | ... AK77: =$B$36/12 -> 4166.6667
A78: Variable Compensation | B78: =MAX(B66,B38)*$B$37/12 -> 4583.3333 | C78: =MAX(C66,C38)*$B$37/12 -> 3208.3333 | D78: =MAX(D66,D38)*$B$37/12 -> 3025 | E78: =MAX(E66,E38)*$B$37/12 -> 4583.3333 | F78: =MAX(F66,F38)*$B$37/12 -> 4583.3333 | G78: =MAX(G66,G38)*$B$37/12 -> 4583.3333 | H78: =MAX(H66,H38)*$B$37/12 -> 4583.3333 | I78: =MAX(I66,I38)*$B$37/12 -> 4583.3333 | J78: =MAX(J66,J38)*$B$37/12 -> 4583.3333 | K78: =$B$37/12 -> 4583.3333 | L78: =$B$37/12 -> 4583.3333 | M78: =$B$37/12 -> 4583.3333 | N78: =$B$37/12 -> 4583.3333 | O78: =$B$37/12 -> 4583.3333 | P78: =$B$37/12 -> 4583.3333 | Q78: =$B$37/12 -> 4583.3333 | R78: =$B$37/12 -> 4583.3333 | ... AK78: =$B$37/12 -> 4583.3333
A79: Overhead | B79: =$B$39/12 -> 2500 | C79: =$B$39/12 -> 2500 | D79: =$B$39/12 -> 2500 | E79: =$B$39/12 -> 2500 | F79: =$B$39/12 -> 2500 | G79: =$B$39/12 -> 2500 | H79: =$B$39/12 -> 2500 | I79: =$B$39/12 -> 2500 | ... AK79: =$B$39/12 -> 2500
A80: Cost of leads required | B80: =B67*(1+$B$40)/$B$51*$B$53*$B$54 -> 850.22135 | C80: =C67*(1+$B$40)/$B$51*$B$53*$B$54 -> 2805.7305 | D80: =D67*(1+$B$40)/$B$51*$B$53*$B$54 -> 5611.4609 | E80: =E67*(1+$B$40)/$B$51*$B$53*$B$54 -> 8502.2135 | F80: =F67*(1+$B$40)/$B$51*$B$53*$B$54 -> 8502.2135 | G80: =G67*(1+$B$40)/$B$51*$B$53*$B$54 -> 8502.2135 | H80: =H67*(1+$B$40)/$B$51*$B$53*$B$54 -> 8502.2135 | I80: =I67*(1+$B$40)/$B$51*$B$53*$B$54 -> 8502.2135 | ... AK80: =AK67*(1+$B$40)/$B$51*$B$53*$B$54 -> 8502.2135
A81: Total Expenses | B81: =SUM(B77:B80) -> 12100.221 | C81: =SUM(C77:C80) -> 12680.73 | D81: =SUM(D77:D80) -> 15303.128 | E81: =SUM(E77:E80) -> 19752.214 | F81: =SUM(F77:F80) -> 19752.214 | G81: =SUM(G77:G80) -> 19752.214 | H81: =SUM(H77:H80) -> 19752.214 | I81: =SUM(I77:I80) -> 19752.214 | ... AK81: =SUM(AK77:AK80) -> 19752.214
A82: Cumulative expenses | B82: =B81 -> 12100.221 | C82: =C81+B82 -> 24780.952 | D82: =D81+C82 -> 40084.079 | E82: =E81+D82 -> 59836.293 | F82: =F81+E82 -> 79588.507 | G82: =G81+F82 -> 99340.72 | H82: =H81+G82 -> 119092.93 | I82: =I81+H82 -> 138845.15 | J82: =J81+I82 -> 158597.36 | ... AK82: =AK81+AJ82 -> 691907.13
A84: Breakeven Analysis | B84: Month 1 | C84: Month 2 | D84: Month 3 | E84: Month 4 | F84: Month 5 | G84: Month 6 | H84: Month 7 | I84: Month 8 | J84: Month 9 | K84: Month 10 | L84: Month 11 | M84: Month 12 | N84: Month 13 | O84: Month 14 | P84: Month 15 | Q84: Month 16 | R84: Month 17 | S84: Month 18 | T84: Month 19 | U84: Month 20 | V84: Month 21 | W84: Month 22 | X84: Month 23 | Y84: Month 24 | Z84: Month 25 | AA84: Month 26 | AB84: Month 27 | AC84: Month 28 | AD84: Month 29 | AE84: Month 30 | AF84: Month 31 | AG84: Month 32 | AH84: Month 33 | AI84: Month 34 | AJ84: Month 35 | AK84: Month 36
A85: Net profit | B85: =B71*$B$48-B81 -> -11864.11 | C85: =C71*$B$48-C81 -> -11668.404 | D85: =D71*$B$48-D81 -> -12745.122 | E85: =E71*$B$48-E81 -> -14865.072 | F85: =F71*$B$48-F81 -> -12565.05 | G85: =G71*$B$48-G81 -> -10293.778 | H85: =H71*$B$48-H81 -> -8050.8978 | I85: =I71*$B$48-I81 -> -5836.0531 | ... AK85: =AK71*$B$48-AK81 -> 46107.168
A86: Cumulative Net Profit | B86: =B73-B82 -> -11864.11 | C86: =C73-C82 -> -23532.514 | D86: =D73-D82 -> -36277.636 | E86: =E73-E82 -> -51142.708 | F86: =F73-F82 -> -63707.758 | G86: =G73-G82 -> -74001.537 | H86: =H73-H82 -> -82052.434 | I86: =I73-I82 -> -87888.488 | ... AK86: =AK73-AK82 -> 544423.94
A104: Part 2: Look at the Overall Economics when Ramping Sales Hires
B106: Month 1 | C106: Month 2 | D106: Month 3 | E106: Month 4 | F106: Month 5 | G106: Month 6 | H106: Month 7 | I106: Month 8 | J106: Month 9 | K106: Month 10 | L106: Month 11 | M106: Month 12 | N106: Month 13 | O106: Month 14 | P106: Month 15 | Q106: Month 16 | R106: Month 17 | S106: Month 18 | T106: Month 19 | U106: Month 20 | V106: Month 21 | W106: Month 22 | X106: Month 23 | Y106: Month 24 | Z106: Month 25 | AA106: Month 26 | AB106: Month 27 | AC106: Month 28 | AD106: Month 29 | AE106: Month 30 | AF106: Month 31 | AG106: Month 32 | AH106: Month 33 | AI106: Month 34 | AJ106: Month 35 | AK106: Month 36
A107: New Sales Hires | B107: 2 | C107: 2 | D107: 2 | E107: 2 | F107: 2 | G107: 2 | H107: 2 | I107: 2 | J107: 2 | K107: 2 | L107: 2 | M107: 2 | N107: 2 | O107: 2 | P107: 2 | Q107: 2 | R107: 2 | S107: 2 | T107: 2 | U107: 2 | V107: 2 | W107: 2 | X107: 2 | Y107: 2 | Z107: 2 | AA107: 2 | AB107: 2 | AC107: 2 | AD107: 2 | AE107: 2 | AF107: 2 | AG107: 2 | AH107: 2 | AI107: 2 | AJ107: 2 | AK107: 2
A109: No of Salespeople at
A110: each stage in lifecycle | B110: Month 1 | C110: Month 2 | D110: Month 3 | E110: Month 4 | F110: Month 5 | G110: Month 6 | H110: Month 7 | I110: Month 8 | J110: Month 9 | K110: Month 10 | L110: Month 11 | M110: Month 12 | N110: Month 13 | O110: Month 14 | P110: Month 15 | Q110: Month 16 | R110: Month 17 | S110: Month 18 | T110: Month 19 | U110: Month 20 | V110: Month 21 | W110: Month 22 | X110: Month 23 | Y110: Month 24 | Z110: Month 25 | AA110: Month 26 | AB110: Month 27 | AC110: Month 28 | AD110: Month 29 | AE110: Month 30 | AF110: Month 31 | AG110: Month 32 | AH110: Month 33 | AI110: Month 34 | AJ110: Month 35 | AK110: Month 36
A111: 1st month | B111: =B107 -> 2 | C111: =C107 -> 2 | D111: =D107 -> 2 | E111: =E107 -> 2 | F111: =F107 -> 2 | G111: =G107 -> 2 | H111: =H107 -> 2 | I111: =I107 -> 2 | ... AK111: =AK107 -> 2
A112: 2nd month | C112: =B111 -> 2 | D112: =C111 -> 2 | E112: =D111 -> 2 | F112: =E111 -> 2 | G112: =F111 -> 2 | H112: =G111 -> 2 | I112: =H111 -> 2 | J112: =I111 -> 2 | ... AK112: =AJ111 -> 2
A113: 3rd month | D113: =C112 -> 2 | E113: =D112 -> 2 | F113: =E112 -> 2 | G113: =F112 -> 2 | H113: =G112 -> 2 | I113: =H112 -> 2 | J113: =I112 -> 2 | K113: =J112 -> 2 | ... AK113: =AJ112 -> 2
A114: 4th month | E114: =D113 -> 2 | F114: =E113 -> 2 | G114: =F113 -> 2 | H114: =G113 -> 2 | I114: =H113 -> 2 | J114: =I113 -> 2 | K114: =J113 -> 2 | L114: =K113 -> 2 | ... AK114: =AJ113 -> 2
A115: 5th month | F115: =E114 -> 2 | G115: =F114 -> 2 | H115: =G114 -> 2 | I115: =H114 -> 2 | J115: =I114 -> 2 | K115: =J114 -> 2 | L115: =K114 -> 2 | M115: =L114 -> 2 | ... AK115: =AJ114 -> 2
A116: 6th month | G116: =F115 -> 2 | H116: =G115 -> 2 | I116: =H115 -> 2 | J116: =I115 -> 2 | K116: =J115 -> 2 | L116: =K115 -> 2 | M116: =L115 -> 2 | N116: =M115 -> 2 | ... AK116: =AJ115 -> 2
A117: 7th month | H117: =G116 -> 2 | I117: =H116 -> 2 | J117: =I116 -> 2 | K117: =J116 -> 2 | L117: =K116 -> 2 | M117: =L116 -> 2 | N117: =M116 -> 2 | O117: =N116 -> 2 | ... AK117: =AJ116 -> 2
A118: 4th month | I118: =H117 -> 2 | J118: =I117 -> 2 | K118: =J117 -> 2 | L118: =K117 -> 2 | M118: =L117 -> 2 | N118: =M117 -> 2 | O118: =N117 -> 2 | P118: =O117 -> 2 | ... AK118: =AJ117 -> 2
A119: 4th month | J119: =I118 -> 2 | K119: =J118 -> 2 | L119: =K118 -> 2 | M119: =L118 -> 2 | N119: =M118 -> 2 | O119: =N118 -> 2 | P119: =O118 -> 2 | Q119: =P118 -> 2 | ... AK119: =AJ118 -> 2
A120: 10th month & Beyond | K120: =J119 -> 2 | L120: =K120+K119 -> 4 | M120: =L120+L119 -> 6 | N120: =M120+M119 -> 8 | O120: =N120+N119 -> 10 | P120: =O120+O119 -> 12 | Q120: =P120+P119 -> 14 | R120: =Q120+Q119 -> 16 | S120: =R120+R119 -> 18 | ... AK120: =AJ120+AJ119 -> 54
A121: Total Sales Headcount | B121: =SUM(B111:B120) -> 2 | C121: =SUM(C111:C120) -> 4 | D121: =SUM(D111:D120) -> 6 | E121: =SUM(E111:E120) -> 8 | F121: =SUM(F111:F120) -> 10 | G121: =SUM(G111:G120) -> 12 | H121: =SUM(H111:H120) -> 14 | I121: =SUM(I111:I120) -> 16 | ... AK121: =SUM(AK111:AK120) -> 72
A122: Total Leads Required | B122: =B126*(1+$B$40)/$B$51*$B$53 -> 13.576389 | C122: =C126*(1+$B$40)/$B$51*$B$53 -> 58.378472 | D122: =D126*(1+$B$40)/$B$51*$B$53 -> 147.98264 | E122: =E126*(1+$B$40)/$B$51*$B$53 -> 283.74653 | F122: =F126*(1+$B$40)/$B$51*$B$53 -> 419.51042 | G122: =G126*(1+$B$40)/$B$51*$B$53 -> 555.27431 | H122: =H126*(1+$B$40)/$B$51*$B$53 -> 691.03819 | I122: =I126*(1+$B$40)/$B$51*$B$53 -> 826.80208 | ... AK122: =AK126*(1+$B$40)/$B$51*$B$53 -> 4628.191
A125: Income | B125: Month 1 | C125: Month 2 | D125: Month 3 | E125: Month 4 | F125: Month 5 | G125: Month 6 | H125: Month 7 | I125: Month 8 | J125: Month 9 | K125: Month 10 | L125: Month 11 | M125: Month 12 | N125: Month 13 | O125: Month 14 | P125: Month 15 | Q125: Month 16 | R125: Month 17 | S125: Month 18 | T125: Month 19 | U125: Month 20 | V125: Month 21 | W125: Month 22 | X125: Month 23 | Y125: Month 24 | Z125: Month 25 | AA125: Month 26 | AB125: Month 27 | AC125: Month 28 | AD125: Month 29 | AE125: Month 30 | AF125: Month 31 | AG125: Month 32 | AH125: Month 33 | AI125: Month 34 | AJ125: Month 35 | AK125: Month 36
A126: Bookings (ACV) | B126: =B$111*$B67+B$112*$C67+B$113*$D67+B$114*$E67+B$115*$F67+B$116*$G67+B$117*$H67+B$118*$I67+B$119*$J67+B$120*$K67 -> 7083.3333 | C126: =C$111*$B67+C$112*$C67+C$113*$D67+C$114*$E67+C$115*$F67+C$116*$G67+C$117*$H67+C$118*$I67+C$119*$J67+C$120*$K67 -> 30458.333 | D126: =D$111*$B67+D$112*$C67+D$113*$D67+D$114*$E67+D$115*$F67+D$116*$G67+D$117*$H67+D$118*$I67+D$119*$J67+D$120*$K67 -> 77208.333 | E126: =E$111*$B67+E$112*$C67+E$113*$D67+E$114*$E67+E$115*$F67+E$116*$G67+E$117*$H67+E$118*$I67+E$119*$J67+E$120*$K67 -> 148041.67 | F126: =F$111*$B67+F$112*$C67+F$113*$D67+F$114*$E67+F$115*$F67+F$116*$G67+F$117*$H67+F$118*$I67+F$119*$J67+F$120*$K67 -> 218875 | G126: =G$111*$B67+G$112*$C67+G$113*$D67+G$114*$E67+G$115*$F67+G$116*$G67+G$117*$H67+G$118*$I67+G$119*$J67+G$120*$K67 -> 289708.33 | H126: =H$111*$B67+H$112*$C67+H$113*$D67+H$114*$E67+H$115*$F67+H$116*$G67+H$117*$H67+H$118*$I67+H$119*$J67+H$120*$K67 -> 360541.67 | I126: =I$111*$B67+I$112*$C67+I$113*$D67+I$114*$E67+I$115*$F67+I$116*$G67+I$117*$H67+I$118*$I67+I$119*$J67+I$120*$K67 -> 431375 | ... AK126: =AK$111*$B67+AK$112*$C67+AK$113*$D67+AK$114*$E67+AK$115*$F67+AK$116*$G67+AK$117*$H67+AK$118*$I67+AK$119*$J67+AK$120*$K67 -> 2414708.3
A127: Total MRR (Billings) | B127: =B126/12 -> 590.27778 | C127: =C126/12+B127*(1-$B$47) -> 3121.0938 | D127: =D126/12+C127*(1-$B$47) -> 9516.1079 | E127: =E126/12+D127*(1-$B$47) -> 21733.962 | F127: =F126/12+E127*(1-$B$47) -> 39701.871 | G127: =G126/12+F127*(1-$B$47) -> 63347.959 | H127: =H126/12+G127*(1-$B$47) -> 92601.248 | I127: =I126/12+H127*(1-$B$47) -> 127391.65 | J127: =J126/12+I127*(1-$B$47) -> 167649.95 | ... AK127: =AK126/12+AJ127*(1-$B$47) -> 3090827.7
A128: Cumulative Billings | B128: =B127 -> 590.27778 | C128: =B128+C127 -> 3711.3715 | D128: =C128+D127 -> 13227.479 | E128: =D128+E127 -> 34961.441 | F128: =E128+F127 -> 74663.312 | G128: =F128+G127 -> 138011.27 | H128: =G128+H127 -> 230612.52 | I128: =H128+I127 -> 358004.17 | J128: =I128+J127 -> 525654.12 | ... AK128: =AJ128+AK127 -> 38492114
A129: Cumulative Gross Profit | B129: =$B$48*B128 -> 472.22222 | C129: =$B$48*C128 -> 2969.0972 | D129: =$B$48*D128 -> 10581.984 | E129: =$B$48*E128 -> 27969.153 | F129: =$B$48*F128 -> 59730.65 | G129: =$B$48*G128 -> 110409.02 | H129: =$B$48*H128 -> 184490.02 | I129: =$B$48*I128 -> 286403.33 | ... AK129: =$B$48*AK128 -> 30793691
A130: Growth in MRR | B130: =B127 -> 590.27778 | C130: =C127-B127 -> 2530.816 | D130: =D127-C127 -> 6395.0141 | E130: =E127-D127 -> 12217.854 | F130: =F127-E127 -> 17967.909 | G130: =G127-F127 -> 23646.088 | H130: =H127-G127 -> 29253.289 | I130: =I127-H127 -> 34790.401 | J130: =J127-I127 -> 40258.299 | ... AK130: =AK127-AJ127 -> 164648.45
A132: Expenses
A133: Base Salary | B133: =B$121*B77 -> 8333.3333 | C133: =C$121*C77 -> 16666.667 | D133: =D$121*D77 -> 25000 | E133: =E$121*E77 -> 33333.333 | F133: =F$121*F77 -> 41666.667 | G133: =G$121*G77 -> 50000 | H133: =H$121*H77 -> 58333.333 | I133: =I$121*I77 -> 66666.667 | ... AK133: =AK$121*AK77 -> 300000
A134: Variable Compensation | B134: =B$111*$B78+B$112*$C78+B$113*$D78+B$114*$E78+B$115*$F78+B$116*$G78+B$117*$H78+B$118*$I78+B$119*$J78+B$120*$K78 -> 9166.6667 | C134: =C$111*$B78+C$112*$C78+C$113*$D78+C$114*$E78+C$115*$F78+C$116*$G78+C$117*$H78+C$118*$I78+C$119*$J78+C$120*$K78 -> 15583.333 | D134: =D$111*$B78+D$112*$C78+D$113*$D78+D$114*$E78+D$115*$F78+D$116*$G78+D$117*$H78+D$118*$I78+D$119*$J78+D$120*$K78 -> 21633.333 | E134: =E$111*$B78+E$112*$C78+E$113*$D78+E$114*$E78+E$115*$F78+E$116*$G78+E$117*$H78+E$118*$I78+E$119*$J78+E$120*$K78 -> 30800 | F134: =F$111*$B78+F$112*$C78+F$113*$D78+F$114*$E78+F$115*$F78+F$116*$G78+F$117*$H78+F$118*$I78+F$119*$J78+F$120*$K78 -> 39966.667 | G134: =G$111*$B78+G$112*$C78+G$113*$D78+G$114*$E78+G$115*$F78+G$116*$G78+G$117*$H78+G$118*$I78+G$119*$J78+G$120*$K78 -> 49133.333 | H134: =H$111*$B78+H$112*$C78+H$113*$D78+H$114*$E78+H$115*$F78+H$116*$G78+H$117*$H78+H$118*$I78+H$119*$J78+H$120*$K78 -> 58300 | I134: =I$111*$B78+I$112*$C78+I$113*$D78+I$114*$E78+I$115*$F78+I$116*$G78+I$117*$H78+I$118*$I78+I$119*$J78+I$120*$K78 -> 67466.667 | ... AK134: =AK$111*$B78+AK$112*$C78+AK$113*$D78+AK$114*$E78+AK$115*$F78+AK$116*$G78+AK$117*$H78+AK$118*$I78+AK$119*$J78+AK$120*$K78 -> 324133.33
A135: Overhead | B135: =B$121*B79 -> 5000 | C135: =C$121*C79 -> 10000 | D135: =D$121*D79 -> 15000 | E135: =E$121*E79 -> 20000 | F135: =F$121*F79 -> 25000 | G135: =G$121*G79 -> 30000 | H135: =H$121*H79 -> 35000 | I135: =I$121*I79 -> 40000 | ... AK135: =AK$121*AK79 -> 180000
A136: Cost of leads required | B136: =B122*$B$54 -> 1700.4427 | C136: =C122*$B$54 -> 7311.9036 | D136: =D122*$B$54 -> 18534.826 | E136: =E122*$B$54 -> 35539.253 | F136: =F122*$B$54 -> 52543.68 | G136: =G122*$B$54 -> 69548.107 | H136: =H122*$B$54 -> 86552.534 | I136: =I122*$B$54 -> 103556.96 | ... AK136: =AK122*$B$54 -> 579680.92
A137: Total Expenses | B137: =SUM(B133:B136) -> 24200.443 | C137: =SUM(C133:C136) -> 49561.904 | D137: =SUM(D133:D136) -> 80168.159 | E137: =SUM(E133:E136) -> 119672.59 | F137: =SUM(F133:F136) -> 159177.01 | G137: =SUM(G133:G136) -> 198681.44 | H137: =SUM(H133:H136) -> 238185.87 | I137: =SUM(I133:I136) -> 277690.29 | ... AK137: =SUM(AK133:AK136) -> 1383814.3
A138: Cumulative expenses | B138: =B137 -> 24200.443 | C138: =C137+B138 -> 73762.346 | D138: =D137+C138 -> 153930.51 | E138: =E137+D138 -> 273603.09 | F138: =F137+E138 -> 432780.1 | G138: =G137+F138 -> 631461.54 | H138: =H137+G138 -> 869647.41 | I138: =I137+H138 -> 1147337.7 | J138: =J137+I138 -> 1464532.4 | ... AK138: =AK137+AJ138 -> 24961463
A140: Breakeven Analysis | B140: Month 1 | C140: Month 2 | D140: Month 3 | E140: Month 4 | F140: Month 5 | G140: Month 6 | H140: Month 7 | I140: Month 8 | J140: Month 9 | K140: Month 10 | L140: Month 11 | M140: Month 12 | N140: Month 13 | O140: Month 14 | P140: Month 15 | Q140: Month 16 | R140: Month 17 | S140: Month 18 | T140: Month 19 | U140: Month 20 | V140: Month 21 | W140: Month 22 | X140: Month 23 | Y140: Month 24 | Z140: Month 25 | AA140: Month 26 | AB140: Month 27 | AC140: Month 28 | AD140: Month 29 | AE140: Month 30 | AF140: Month 31 | AG140: Month 32 | AH140: Month 33 | AI140: Month 34 | AJ140: Month 35 | AK140: Month 36
A141: Net profit | B141: =B127*$B$48-B137 -> -23728.22 | C141: =C127*$B$48-C137 -> -47065.029 | D141: =D127*$B$48-D137 -> -72555.273 | E141: =E127*$B$48-E137 -> -102285.42 | F141: =F127*$B$48-F137 -> -127415.52 | G141: =G127*$B$48-G137 -> -148003.07 | H141: =H127*$B$48-H137 -> -164104.87 | I141: =I127*$B$48-I137 -> -175776.98 | ... AK141: =AK127*$B$48-AK137 -> 1088847.9
A142: Cumulative Net Profit | B142: =B129-B138 -> -23728.22 | C142: =C129-C138 -> -70793.249 | D142: =D129-D138 -> -143348.52 | E142: =E129-E138 -> -245633.94 | F142: =F129-F138 -> -373049.45 | G142: =G129-G138 -> -521052.53 | H142: =H129-H138 -> -685157.4 | I142: =I129-I138 -> -860934.37 | ... AK142: =AK129-AK138 -> 5832227.6
A177: Part 3: Look at the impact of collecting 1 year's payment in advance
A179: Step 1: Individual Sales person
A180: Income | B180: Month 1 | C180: Month 2 | D180: Month 3 | E180: Month 4 | F180: Month 5 | G180: Month 6 | H180: Month 7 | I180: Month 8 | J180: Month 9 | K180: Month 10 | L180: Month 11 | M180: Month 12 | N180: Month 13 | O180: Month 14 | P180: Month 15 | Q180: Month 16 | R180: Month 17 | S180: Month 18 | T180: Month 19 | U180: Month 20 | V180: Month 21 | W180: Month 22 | X180: Month 23 | Y180: Month 24 | Z180: Month 25 | AA180: Month 26 | AB180: Month 27 | AC180: Month 28 | AD180: Month 29 | AE180: Month 30 | AF180: Month 31 | AG180: Month 32 | AH180: Month 33 | AI180: Month 34 | AJ180: Month 35 | AK180: Month 36
A181: Productivity Ramp | B181: 0.1 | C181: 0.33 | D181: 0.66 | E181: 1 | F181: 1 | G181: 1 | H181: 1 | I181: 1 | J181: 1 | K181: 1 | L181: 1 | M181: 1 | N181: 1 | O181: 1 | P181: 1 | Q181: 1 | R181: 1 | S181: 1 | T181: 1 | U181: 1 | V181: 1 | W181: 1 | X181: 1 | Y181: 1 | Z181: 1 | AA181: 1 | AB181: 1 | AC181: 1 | AD181: 1 | AE181: 1 | AF181: 1 | AG181: 1 | AH181: 1 | AI181: 1 | AJ181: 1 | AK181: 1
A182: Bookings (ACV) | B182: =B181*$B$44*(1-$B$40) -> 3541.6667 | C182: =C181*$B$44*(1-$B$40) -> 11687.5 | D182: =D181*$B$44*(1-$B$40) -> 23375 | E182: =E181*$B$44*(1-$B$40) -> 35416.667 | F182: =F181*$B$44*(1-$B$40) -> 35416.667 | G182: =G181*$B$44*(1-$B$40) -> 35416.667 | H182: =H181*$B$44*(1-$B$40) -> 35416.667 | I182: =I181*$B$44*(1-$B$40) -> 35416.667 | ... AK182: =AK181*$B$44*(1-$B$40) -> 35416.667
A183: Renewable contract value | M183: =B182 -> 3541.6667 | N183: =C182 -> 11687.5 | O183: =D182 -> 23375 | P183: =E182 -> 35416.667 | Q183: =F182 -> 35416.667 | R183: =G182 -> 35416.667 | S183: =H182 -> 35416.667 | T183: =I182 -> 35416.667 | ... Y183: =N182 -> 35416.667 | Z183: =M182+M185 -> 38427.083 | AA183: =N182+N185 -> 45351.042 | AB183: =O182+O185 -> 55285.417 | AC183: =P182+P185 -> 65520.833 | AD183: =Q182+Q185 -> 65520.833 | AE183: =R182+R185 -> 65520.833 | AF183: =S182+S185 -> 65520.833 | AG183: =T182+T185 -> 65520.833 | ... AK183: =X182+X185 -> 65520.833
A184: Churn | M184: =-$B$47*12*M183 -> -531.25 | N184: =-$B$47*12*N183 -> -1753.125 | O184: =-$B$47*12*O183 -> -3506.25 | P184: =-$B$47*12*P183 -> -5312.5 | Q184: =-$B$47*12*Q183 -> -5312.5 | R184: =-$B$47*12*R183 -> -5312.5 | S184: =-$B$47*12*S183 -> -5312.5 | T184: =-$B$47*12*T183 -> -5312.5 | ... AK184: =-$B$47*12*AK183 -> -9828.125
A185: Renewals (renewable - churn) | M185: =M183+M184 -> 3010.4167 | N185: =N183+N184 -> 9934.375 | O185: =O183+O184 -> 19868.75 | P185: =P183+P184 -> 30104.167 | Q185: =Q183+Q184 -> 30104.167 | R185: =R183+R184 -> 30104.167 | S185: =S183+S184 -> 30104.167 | T185: =T183+T184 -> 30104.167 | ... AK185: =AK183+AK184 -> 55692.708
A186: Billings (bookings + renewals) | B186: =B182 -> 3541.6667 | C186: =C182 -> 11687.5 | D186: =D182 -> 23375 | E186: =E182 -> 35416.667 | F186: =F182 -> 35416.667 | G186: =G182 -> 35416.667 | H186: =H182 -> 35416.667 | I186: =I182 -> 35416.667 | ... L186: =L182 -> 35416.667 | M186: =M182+M185 -> 38427.083 | N186: =N182+N185 -> 45351.042 | O186: =O182+O185 -> 55285.417 | P186: =P182+P185 -> 65520.833 | Q186: =Q182+Q185 -> 65520.833 | R186: =R182+R185 -> 65520.833 | S186: =S182+S185 -> 65520.833 | T186: =T182+T185 -> 65520.833 | ... AK186: =AK182+AK185 -> 91109.375
A187: Cumulative Billings | B187: =B186 -> 3541.6667 | C187: =B187+C186 -> 15229.167 | D187: =C187+D186 -> 38604.167 | E187: =D187+E186 -> 74020.833 | F187: =E187+F186 -> 109437.5 | G187: =F187+G186 -> 144854.17 | H187: =G187+H186 -> 180270.83 | I187: =H187+I186 -> 215687.5 | J187: =I187+J186 -> 251104.17 | ... AK187: =AJ187+AK186 -> 2160647.8
A188: Cumulative Gross Profit | B188: =$B$48*B187 -> 2833.3333 | C188: =$B$48*C187 -> 12183.333 | D188: =$B$48*D187 -> 30883.333 | E188: =$B$48*E187 -> 59216.667 | F188: =$B$48*F187 -> 87550 | G188: =$B$48*G187 -> 115883.33 | H188: =$B$48*H187 -> 144216.67 | I188: =$B$48*I187 -> 172550 | ... AK188: =$B$48*AK187 -> 1728518.2
A191: Breakeven Analysis | B191: Month 1 | C191: Month 2 | D191: Month 3 | E191: Month 4 | F191: Month 5 | G191: Month 6 | H191: Month 7 | I191: Month 8 | J191: Month 9 | K191: Month 10 | L191: Month 11 | M191: Month 12 | N191: Month 13 | O191: Month 14 | P191: Month 15 | Q191: Month 16 | R191: Month 17 | S191: Month 18 | T191: Month 19 | U191: Month 20 | V191: Month 21 | W191: Month 22 | X191: Month 23 | Y191: Month 24 | Z191: Month 25 | AA191: Month 26 | AB191: Month 27 | AC191: Month 28 | AD191: Month 29 | AE191: Month 30 | AF191: Month 31 | AG191: Month 32 | AH191: Month 33 | AI191: Month 34 | AJ191: Month 35 | AK191: Month 36
A192: Net Cash Flows | B192: =B186*$B$48-B81 -> -9266.888 | C192: =C186*$B$48-C81 -> -3330.7305 | D192: =D186*$B$48-D81 -> 3396.8724 | E192: =E186*$B$48-E81 -> 8581.1198 | F192: =F186*$B$48-F81 -> 8581.1198 | G192: =G186*$B$48-G81 -> 8581.1198 | H192: =H186*$B$48-H81 -> 8581.1198 | I192: =I186*$B$48-I81 -> 8581.1198 | ... AK192: =AK186*$B$48-AK81 -> 53135.286
A193: Cumulative Net Cash Flows | B193: =B188-B82 -> -9266.888 | C193: =C188-C82 -> -12597.618 | D193: =D188-D82 -> -9200.7461 | E193: =E188-E82 -> -619.6263 | F193: =F188-F82 -> 7961.4935 | G193: =G188-G82 -> 16542.613 | H193: =H188-H82 -> 25123.733 | I193: =I188-I82 -> 33704.853 | ... AK193: =AK188-AK82 -> 1036611.1
...
